{
  "id_sptag": "-980186384",
  "index_page": 0,
  "name_cl_sptag": "Hatoba Tsugu",
  "name_parent": "Anime",
  "total_img": 5,
  "total_page": 0,
  "hc_lt_alb": "-760531221",
  "hc_lt_data_img": "-1890614400",
  "hc_lt_nortag": "-1076468788",
  "hc_lt_sptag": "-1871178915",
  "lt_alb": [
    {
      "id_alb": "63410260",
      "name_alb": "Anime",
      "total_img": 85314
    }
  ],
  "lt_data_img": [
    {
      "hc_lt_id_alb": "-824026795",
      "hc_lt_id_nortag": "743211583",
      "hc_lt_id_sptag": "-1781098769",
      "id_img": "VirtualYoutuber_913220_crop2608_1170008602",
      "link_img": "UTb0sGqADnbLiHq9qhRMRkSRiLND0Tk7ctN8tpraiicYIZVf48xOi5j92IwZ3R5DqXHceHEQA1gjyv9sM6QcX5Vy4706IhQgSYlgwrgVRHU=",
      "thumb": "UTb0sGqADnbLiHq9qhRMRkSRiLND0Tk7ctN8tpraiicYIZVf48xOi5j92IwZ3R5DIG0cC+sMNpRmY+kAzEC6mZVy4706IhQgSYlgwrgVRHU=",
      "lt_id_alb": [
        "63410260"
      ],
      "list_id_nortag": [
        "-52636355",
        "-1182628656"
      ],
      "lt_id_sptag": [
        "-2017515920",
        "1545739930",
        "-1546073662",
        "117222074",
        "538504409",
        "-1450260536",
        "-980186384",
        "1541647243",
        "1813151526",
        "1078827483",
        "491824726",
        "1410951528"
      ]
    },
    {
      "hc_lt_id_alb": "-824026795",
      "hc_lt_id_nortag": "743211583",
      "hc_lt_id_sptag": "771251969",
      "id_img": "VirtualYoutuber_949205_crop2608_-929647120",
      "link_img": "UTb0sGqADnbLiHq9qhRMRkSRiLND0Tk7ctN8tpraiieO3Ua72u1I3Vo2MkAUoHnrO/frBvmS89wzQmOq3Ux2cJVy4706IhQgSYlgwrgVRHU=",
      "thumb": "UTb0sGqADnbLiHq9qhRMRkSRiLND0Tk7ctN8tpraiieO3Ua72u1I3Vo2MkAUoHnrlPmkSqXTVMLXUQrtdPuEx5Vy4706IhQgSYlgwrgVRHU=",
      "lt_id_alb": [
        "63410260"
      ],
      "list_id_nortag": [
        "-52636355",
        "-1182628656"
      ],
      "lt_id_sptag": [
        "-1216236529",
        "-1937610099",
        "1755521698",
        "117222074",
        "-1686571485",
        "-980186384",
        "1541647243",
        "680065126",
        "-1823594757",
        "1078827483",
        "1410951528"
      ]
    },
    {
      "hc_lt_id_alb": "-824026795",
      "hc_lt_id_nortag": "743211583",
      "hc_lt_id_sptag": "-1958934976",
      "id_img": "VirtualYoutuber_910993_crop2608_1169926176",
      "link_img": "UTb0sGqADnbLiHq9qhRMRkSRiLND0Tk7ctN8tpraiieFJ8GKalYREJtdOUTjBhncWouujDAsergimU3DpfWhx5Vy4706IhQgSYlgwrgVRHU=",
      "thumb": "UTb0sGqADnbLiHq9qhRMRkSRiLND0Tk7ctN8tpraiieFJ8GKalYREJtdOUTjBhncIyI0G+wWPHY3nohrmRRNUpVy4706IhQgSYlgwrgVRHU=",
      "lt_id_alb": [
        "63410260"
      ],
      "list_id_nortag": [
        "-52636355",
        "-1182628656"
      ],
      "lt_id_sptag": [
        "1755521698",
        "117222074",
        "-980186384",
        "1541647243",
        "-1165766878",
        "1078827483",
        "491824726",
        "1410951528"
      ]
    },
    {
      "hc_lt_id_alb": "-824026795",
      "hc_lt_id_nortag": "743211583",
      "hc_lt_id_sptag": "1763479631",
      "id_img": "VirtualYoutuber_931882_crop2608_-1185601678",
      "link_img": "UTb0sGqADnbLiHq9qhRMRkSRiLND0Tk7ctN8tpraiieFjLdHyzQN/i8G9QiXPiuT6m2qIu5FBzA1j3+39JyrEpVy4706IhQgSYlgwrgVRHU=",
      "thumb": "UTb0sGqADnbLiHq9qhRMRkSRiLND0Tk7ctN8tpraiieFjLdHyzQN/i8G9QiXPiuTeEF6M0o0mKhiIrCIvHg5R5Vy4706IhQgSYlgwrgVRHU=",
      "lt_id_alb": [
        "63410260"
      ],
      "list_id_nortag": [
        "-52636355",
        "-1182628656"
      ],
      "lt_id_sptag": [
        "1545739930",
        "-1230434216",
        "117222074",
        "-980186384",
        "1541647243",
        "1813151526",
        "1078827483",
        "491824726",
        "1410951528"
      ]
    },
    {
      "hc_lt_id_alb": "-824026795",
      "hc_lt_id_nortag": "743211583",
      "hc_lt_id_sptag": "-2136212948",
      "id_img": "VirtualYoutuber_956269_crop2608_-110867054",
      "link_img": "UTb0sGqADnbLiHq9qhRMRkSRiLND0Tk7ctN8tpraiicU77FgT5jn3d/OQxllQ3+ecYmdEthvwuRbQGkjjYCkYZVy4706IhQgSYlgwrgVRHU=",
      "thumb": "UTb0sGqADnbLiHq9qhRMRkSRiLND0Tk7ctN8tpraiicU77FgT5jn3d/OQxllQ3+eMH7kCDAmkf7gqK1kr0KkF5Vy4706IhQgSYlgwrgVRHU=",
      "lt_id_alb": [
        "63410260"
      ],
      "list_id_nortag": [
        "-52636355",
        "-1182628656"
      ],
      "lt_id_sptag": [
        "-1937610099",
        "117222074",
        "-1092439432",
        "-980186384",
        "929761085",
        "1541647243",
        "1508952095",
        "-1176638482",
        "-899599709",
        "1078827483",
        "1410951528"
      ]
    }
  ],
  "lt_nortag": [
    {
      "id_nortag": "-1182628656",
      "name_cl_nortag": "Girls",
      "total_img": 68557,
      "name_parent": "Anime"
    },
    {
      "id_nortag": "-52636355",
      "name_cl_nortag": "Virtual Youtuber",
      "total_img": 105,
      "name_parent": "Anime"
    }
  ],
  "lt_sptag": [
    {
      "id_sptag": "-1176638482",
      "name_cl_sptag": "Dark Black",
      "name_parent": "Anime",
      "total": 4051
    },
    {
      "id_sptag": "491824726",
      "name_cl_sptag": "Girls Cute Cool",
      "name_parent": "Anime",
      "total": 31431
    },
    {
      "id_sptag": "-1092439432",
      "name_cl_sptag": "Girls Dark",
      "name_parent": "Anime",
      "total": 3468
    },
    {
      "id_sptag": "-899599709",
      "name_cl_sptag": "Girls Eyes Black",
      "name_parent": "Anime",
      "total": 5810
    },
    {
      "id_sptag": "1545739930",
      "name_cl_sptag": "Girls Eyes Brown",
      "name_parent": "Anime",
      "total": 9376
    },
    {
      "id_sptag": "1755521698",
      "name_cl_sptag": "Girls Eyes Yellow",
      "name_parent": "Anime",
      "total": 6605
    },
    {
      "id_sptag": "538504409",
      "name_cl_sptag": "Girls Hair 2 Color",
      "name_parent": "Anime",
      "total": 1686
    },
    {
      "id_sptag": "-1686571485",
      "name_cl_sptag": "Girls Hair Black",
      "name_parent": "Anime",
      "total": 16737
    },
    {
      "id_sptag": "-1450260536",
      "name_cl_sptag": "Girls Hair Blue",
      "name_parent": "Anime",
      "total": 9528
    },
    {
      "id_sptag": "1813151526",
      "name_cl_sptag": "Girls Hair Brow",
      "name_parent": "Anime",
      "total": 13760
    },
    {
      "id_sptag": "-1937610099",
      "name_cl_sptag": "Girls Hair Grey",
      "name_parent": "Anime",
      "total": 9239
    },
    {
      "id_sptag": "-1823594757",
      "name_cl_sptag": "Girls Hair Silver",
      "name_parent": "Anime",
      "total": 16300
    },
    {
      "id_sptag": "-1165766878",
      "name_cl_sptag": "Girls Hair Yellow",
      "name_parent": "Anime",
      "total": 12651
    },
    {
      "id_sptag": "117222074",
      "name_cl_sptag": "Girls Hats",
      "name_parent": "Anime",
      "total": 11965
    },
    {
      "id_sptag": "-1546073662",
      "name_cl_sptag": "Girls Loli",
      "name_parent": "Anime",
      "total": 2098
    },
    {
      "id_sptag": "680065126",
      "name_cl_sptag": "Girls Sad",
      "name_parent": "Anime",
      "total": 10506
    },
    {
      "id_sptag": "-2017515920",
      "name_cl_sptag": "Girls Sharp Canine Tooth",
      "name_parent": "Anime",
      "total": 3202
    },
    {
      "id_sptag": "1410951528",
      "name_cl_sptag": "Girls Short Hair",
      "name_parent": "Anime",
      "total": 23769
    },
    {
      "id_sptag": "-1230434216",
      "name_cl_sptag": "Girls Smile",
      "name_parent": "Anime",
      "total": 24284
    },
    {
      "id_sptag": "1541647243",
      "name_cl_sptag": "Girls Student",
      "name_parent": "Anime",
      "total": 16308
    },
    {
      "id_sptag": "1078827483",
      "name_cl_sptag": "Girls Tie Bows",
      "name_parent": "Anime",
      "total": 61257
    },
    {
      "id_sptag": "1508952095",
      "name_cl_sptag": "Girls Water Rain",
      "name_parent": "Anime",
      "total": 2954
    },
    {
      "id_sptag": "-980186384",
      "name_cl_sptag": "Hatoba Tsugu",
      "name_parent": "Anime",
      "total": 5
    },
    {
      "id_sptag": "-1216236529",
      "name_cl_sptag": "Sad",
      "name_parent": "Anime",
      "total": 12057
    },
    {
      "id_sptag": "929761085",
      "name_cl_sptag": "Umbrella",
      "name_parent": "Anime",
      "total": 120
    }
  ]
}