{
  "id_sptag": "1367612750",
  "index_page": 0,
  "name_cl_sptag": "Headband",
  "name_parent": "Anime",
  "total_img": 73,
  "total_page": 0,
  "hc_lt_alb": "-760531221",
  "hc_lt_data_img": "-610542554",
  "hc_lt_nortag": "137598703",
  "hc_lt_sptag": "-1296810932",
  "lt_alb": [
    {
      "id_alb": "63410260",
      "name_alb": "Anime",
      "total_img": 85314
    }
  ],
  "lt_data_img": [
    {
      "hc_lt_id_alb": "-824026795",
      "hc_lt_id_nortag": "-490473962",
      "hc_lt_id_sptag": "210109691",
      "id_img": "Aikatsu_712046_crop2608_-1762077759",
      "link_img": "UTb0sGqADnbLiHq9qhRMRkSRiLND0Tk7ctN8tpraiifRQWcqaHy7rpD+Eh28a+mdllCLO39vnB4NMwJJ8/M4vZVy4706IhQgSYlgwrgVRHU=",
      "thumb": "UTb0sGqADnbLiHq9qhRMRkSRiLND0Tk7ctN8tpraiifRQWcqaHy7rpD+Eh28a+mdNV3RJT4u1NKFLzlF6Y4nOpVy4706IhQgSYlgwrgVRHU=",
      "lt_id_alb": [
        "63410260"
      ],
      "list_id_nortag": [
        "-1182628656",
        "671033425"
      ],
      "lt_id_sptag": [
        "1545739930",
        "-1230434216",
        "-729883027",
        "-353024394",
        "1367612750",
        "1913692055",
        "-67611207",
        "1813151526",
        "-1165766878",
        "1078827483",
        "491824726"
      ]
    },
    {
      "hc_lt_id_alb": "-824026795",
      "hc_lt_id_nortag": "322817577",
      "hc_lt_id_sptag": "691576066",
      "id_img": "DagashiKashi_679709_crop2608_1744313528",
      "link_img": "UTb0sGqADnbLiHq9qhRMRkSRiLND0Tk7ctN8tpraiicrjfH/Fekdk0pE0UxfBPLl1ylOaNHszUgs8oL4LaC1A5Vy4706IhQgSYlgwrgVRHU=",
      "thumb": "UTb0sGqADnbLiHq9qhRMRkSRiLND0Tk7ctN8tpraiicrjfH/Fekdk0pE0UxfBPLlT/Ixpxt09UtaVNjsBaBWKJVy4706IhQgSYlgwrgVRHU=",
      "lt_id_alb": [
        "63410260"
      ],
      "list_id_nortag": [
        "1095644500",
        "-1182628656"
      ],
      "lt_id_sptag": [
        "-1230434216",
        "643795693",
        "1367612750",
        "376240968",
        "63311442",
        "1078827483",
        "-660511924",
        "2137211747",
        "26918368",
        "1410951528",
        "1414196206"
      ]
    },
    {
      "hc_lt_id_alb": "-824026795",
      "hc_lt_id_nortag": "-1662551372",
      "hc_lt_id_sptag": "-1633048745",
      "id_img": "KantaiCollection_792972_crop2608_2048596006",
      "link_img": "UTb0sGqADnbLiHq9qhRMRkSRiLND0Tk7ctN8tpraiiddkmO02NwECn2SZ3iq7YNy02lf5jQJvpB4kpmEuc6A2pVy4706IhQgSYlgwrgVRHU=",
      "thumb": "UTb0sGqADnbLiHq9qhRMRkSRiLND0Tk7ctN8tpraiiddkmO02NwECn2SZ3iq7YNyBk5cD2I74sfjDOKhp9T9TJVy4706IhQgSYlgwrgVRHU=",
      "lt_id_alb": [
        "63410260"
      ],
      "list_id_nortag": [
        "579558099",
        "-1182628656"
      ],
      "lt_id_sptag": [
        "1545739930",
        "-678792093",
        "-1372583199",
        "750914149",
        "-1230434216",
        "473789866",
        "1945436082",
        "-667683750",
        "-1068725006",
        "1367612750",
        "376240968",
        "-1450260536",
        "1813151526",
        "-1152882625",
        "1078827483",
        "-1456680780",
        "-1042073588",
        "1410951528"
      ]
    },
    {
      "hc_lt_id_alb": "-824026795",
      "hc_lt_id_nortag": "-2092928010",
      "hc_lt_id_sptag": "-1765620636",
      "id_img": "Original_907801_crop2608_1402460633",
      "link_img": "UTb0sGqADnbLiHq9qhRMRkSRiLND0Tk7ctN8tpraiic9FhCTNiLcOUuVibN9Q+YXtnFEVF5Lhi57QEPJORUvsJVy4706IhQgSYlgwrgVRHU=",
      "thumb": "UTb0sGqADnbLiHq9qhRMRkSRiLND0Tk7ctN8tpraiic9FhCTNiLcOUuVibN9Q+YX5IL/BnY7s5L5QHWc0QsHIJVy4706IhQgSYlgwrgVRHU=",
      "lt_id_alb": [
        "63410260"
      ],
      "list_id_nortag": [
        "-1182628656",
        "-1556851449"
      ],
      "lt_id_sptag": [
        "-1230434216",
        "-729883027",
        "-353024394",
        "1367612750",
        "-67611207",
        "-260062140",
        "-1165766878",
        "-1046579185",
        "1078827483",
        "2137211747"
      ]
    },
    {
      "hc_lt_id_alb": "-824026795",
      "hc_lt_id_nortag": "-1114397356",
      "hc_lt_id_sptag": "1143614925",
      "id_img": "Original_916032_crop2608_-705532591",
      "link_img": "UTb0sGqADnbLiHq9qhRMRkSRiLND0Tk7ctN8tpraiidazm88IyDj4SeI0kt38Sv+uYtEui51eEWRNoiljOtqv5Vy4706IhQgSYlgwrgVRHU=",
      "thumb": "UTb0sGqADnbLiHq9qhRMRkSRiLND0Tk7ctN8tpraiidazm88IyDj4SeI0kt38Sv+27EwjA3iyG5uQxkReqaMWpVy4706IhQgSYlgwrgVRHU=",
      "lt_id_alb": [
        "63410260"
      ],
      "list_id_nortag": [
        "-669347768",
        "-1182628656"
      ],
      "lt_id_sptag": [
        "1271392973",
        "1414468990",
        "-220048903",
        "-333189356",
        "1267158087",
        "1367612750",
        "376240968",
        "-260062140",
        "-1823594757",
        "1078827483",
        "2137211747",
        "1410951528"
      ]
    },
    {
      "hc_lt_id_alb": "-824026795",
      "hc_lt_id_nortag": "-962447637",
      "hc_lt_id_sptag": "-1987826431",
      "id_img": "PuellaMagiMadokaMagica_226728_crop2608_208223064",
      "link_img": "UTb0sGqADnbLiHq9qhRMRkSRiLND0Tk7ctN8tpraiifmhBZAoayF/NW0nxSV0VxSpBx+EHMHrCnlu4xrh29luJVy4706IhQgSYlgwrgVRHU=",
      "thumb": "UTb0sGqADnbLiHq9qhRMRkSRiLND0Tk7ctN8tpraiifmhBZAoayF/NW0nxSV0VxSVoi/0KctIqfMvkuerB2MgpVy4706IhQgSYlgwrgVRHU=",
      "lt_id_alb": [
        "63410260"
      ],
      "list_id_nortag": [
        "-1823434899",
        "-1182628656"
      ],
      "lt_id_sptag": [
        "-2017515920",
        "641041541",
        "1545739930",
        "1037188654",
        "-2024578405",
        "-353024394",
        "1367612750",
        "-1866523531",
        "-67611207",
        "1627623413",
        "1813151526",
        "1089393616",
        "-1455727370",
        "1078827483",
        "-1456680780",
        "-343568313",
        "2137211747"
      ]
    },
    {
      "hc_lt_id_alb": "-824026795",
      "hc_lt_id_nortag": "-739215050",
      "hc_lt_id_sptag": "-59102901",
      "id_img": "TokyoGhoul_596868_crop2608_-329826835",
      "link_img": "UTb0sGqADnbLiHq9qhRMRkSRiLND0Tk7ctN8tpraiidj+lrw5Mz5r7/SQ9bBNqSntxKrfEOPW1FLnqFrKHj8QZVy4706IhQgSYlgwrgVRHU=",
      "thumb": "UTb0sGqADnbLiHq9qhRMRkSRiLND0Tk7ctN8tpraiidj+lrw5Mz5r7/SQ9bBNqSnjdCPNFyzM1OHBSGEq5/zPJVy4706IhQgSYlgwrgVRHU=",
      "lt_id_alb": [
        "63410260"
      ],
      "list_id_nortag": [
        "882178788"
      ],
      "lt_id_sptag": [
        "177416588",
        "-1239845591",
        "-1491861316",
        "-42452310",
        "1367612750",
        "-1307705100",
        "1171821264",
        "-1730597006",
        "-2046828957",
        "1623277449"
      ]
    },
    {
      "hc_lt_id_alb": "-824026795",
      "hc_lt_id_nortag": "-822968574",
      "hc_lt_id_sptag": "493310477",
      "id_img": "MissKobayashisDragonMaid_881181_crop2608_2037728034",
      "link_img": "UTb0sGqADnbLiHq9qhRMRkSRiLND0Tk7ctN8tpraiifxa3D21jeo8nnIatyhgBpDVYo1Oq87JJW4qm0763itnJVy4706IhQgSYlgwrgVRHU=",
      "thumb": "UTb0sGqADnbLiHq9qhRMRkSRiLND0Tk7ctN8tpraiifxa3D21jeo8nnIatyhgBpDMwsFU0/ztNA5tlJuApmuZJVy4706IhQgSYlgwrgVRHU=",
      "lt_id_alb": [
        "63410260"
      ],
      "list_id_nortag": [
        "807641379",
        "-1182628656"
      ],
      "lt_id_sptag": [
        "-2017515920",
        "-1216236529",
        "702196920",
        "-1130112717",
        "606716576",
        "-1230434216",
        "697180300",
        "-353024394",
        "1367612750",
        "246776394",
        "63311442",
        "-67611207",
        "1627623413",
        "680065126",
        "-1353196196",
        "-1165766878",
        "1526533345",
        "1078827483",
        "-1456680780",
        "2137211747"
      ]
    },
    {
      "hc_lt_id_alb": "-824026795",
      "hc_lt_id_nortag": "-1532318063",
      "hc_lt_id_sptag": "-1948480907",
      "id_img": "SaekanoHowtoRaiseaBoringGirlfriend_679014_crop2608_880492195",
      "link_img": "UTb0sGqADnbLiHq9qhRMRkSRiLND0Tk7ctN8tpraiidefdH7iOixb7WzO+v7aGxwHVOLi2V4Y9CnUHqnhgmqP5Vy4706IhQgSYlgwrgVRHU=",
      "thumb": "UTb0sGqADnbLiHq9qhRMRkSRiLND0Tk7ctN8tpraiidefdH7iOixb7WzO+v7aGxwmc1YHMTKO/nSc5WXT9NvVZVy4706IhQgSYlgwrgVRHU=",
      "lt_id_alb": [
        "63410260"
      ],
      "list_id_nortag": [
        "1589031968",
        "-1182628656"
      ],
      "lt_id_sptag": [
        "-1915687819",
        "-1230434216",
        "29436897",
        "-353024394",
        "1367612750",
        "-1686571485",
        "-67611207",
        "1541647243",
        "1813151526",
        "891036203",
        "1078827483"
      ]
    },
    {
      "hc_lt_id_alb": "-824026795",
      "hc_lt_id_nortag": "2062560928",
      "hc_lt_id_sptag": "617337911",
      "id_img": "SoundHorizon_685160_crop2608_-1781628405",
      "link_img": "UTb0sGqADnbLiHq9qhRMRkSRiLND0Tk7ctN8tpraiicxCrENb8vWgtx0WoCTxvG2BXVW4ipNoyWKMIfzJSs2gpVy4706IhQgSYlgwrgVRHU=",
      "thumb": "UTb0sGqADnbLiHq9qhRMRkSRiLND0Tk7ctN8tpraiicxCrENb8vWgtx0WoCTxvG2+cHBskYJuK07bqkO39vSFpVy4706IhQgSYlgwrgVRHU=",
      "lt_id_alb": [
        "63410260"
      ],
      "list_id_nortag": [
        "22161571",
        "-1182628656"
      ],
      "lt_id_sptag": [
        "1271392973",
        "-1937610099",
        "-729883027",
        "-353024394",
        "538504409",
        "1367612750",
        "376240968",
        "-1353196196",
        "-1165766878",
        "-1823594757",
        "-1882261033",
        "1078827483",
        "2137211747",
        "1457245087",
        "176756002"
      ]
    },
    {
      "hc_lt_id_alb": "-824026795",
      "hc_lt_id_nortag": "1896949049",
      "hc_lt_id_sptag": "1840009455",
      "id_img": "SoranoMukoudeSakimasuyouni_792672_crop2608_661604664",
      "link_img": "UTb0sGqADnbLiHq9qhRMRkSRiLND0Tk7ctN8tpraiifzytpBSPQIxcsQrAzu+gkUZdsOC2AupD2W+QkbdUTCbJVy4706IhQgSYlgwrgVRHU=",
      "thumb": "UTb0sGqADnbLiHq9qhRMRkSRiLND0Tk7ctN8tpraiifzytpBSPQIxcsQrAzu+gkUXVQcAoIn6B7F7Bln2Y5pH5Vy4706IhQgSYlgwrgVRHU=",
      "lt_id_alb": [
        "63410260"
      ],
      "list_id_nortag": [
        "-1182628656",
        "-1441071755"
      ],
      "lt_id_sptag": [
        "-1393218324",
        "866423119",
        "-1230434216",
        "-353024394",
        "1367612750",
        "376240968",
        "-290487968",
        "-1165766878",
        "1078827483",
        "2137211747"
      ]
    },
    {
      "hc_lt_id_alb": "-824026795",
      "hc_lt_id_nortag": "-1114397356",
      "hc_lt_id_sptag": "-488078036",
      "id_img": "Original_919728_crop2608_-1847605924",
      "link_img": "UTb0sGqADnbLiHq9qhRMRkSRiLND0Tk7ctN8tpraiicxLIYUthOSwUgXsC3LN7hrrJ2PAxZg0mUl+f0RpSPeMpVy4706IhQgSYlgwrgVRHU=",
      "thumb": "UTb0sGqADnbLiHq9qhRMRkSRiLND0Tk7ctN8tpraiicxLIYUthOSwUgXsC3LN7hrm9c62LyeW2OvSb2KXErBk5Vy4706IhQgSYlgwrgVRHU=",
      "lt_id_alb": [
        "63410260"
      ],
      "list_id_nortag": [
        "-669347768",
        "-1182628656"
      ],
      "lt_id_sptag": [
        "1010924017",
        "-1230434216",
        "1755521698",
        "-353024394",
        "1367612750",
        "-67611207",
        "424462971",
        "1078827483",
        "-1456680780",
        "491824726",
        "-1358769180"
      ]
    },
    {
      "hc_lt_id_alb": "-824026795",
      "hc_lt_id_nortag": "-822968574",
      "hc_lt_id_sptag": "1346137281",
      "id_img": "MissKobayashisDragonMaid_881183_crop2608_1341557806",
      "link_img": "UTb0sGqADnbLiHq9qhRMRkSRiLND0Tk7ctN8tpraiidN9f2Mwr0rk+famx3PiXrwY5JsM59sxCpydaoQHnpNrJVy4706IhQgSYlgwrgVRHU=",
      "thumb": "UTb0sGqADnbLiHq9qhRMRkSRiLND0Tk7ctN8tpraiidN9f2Mwr0rk+famx3PiXrwopfY2Yd2CwMc32Vziy3XHZVy4706IhQgSYlgwrgVRHU=",
      "lt_id_alb": [
        "63410260"
      ],
      "list_id_nortag": [
        "807641379",
        "-1182628656"
      ],
      "lt_id_sptag": [
        "-2017515920",
        "702196920",
        "-1130112717",
        "-375059391",
        "606716576",
        "-1546073662",
        "-353024394",
        "538504409",
        "1367612750",
        "376240968",
        "63311442",
        "-67611207",
        "886532079",
        "1089393616",
        "-1823594757",
        "-1025861007",
        "1078827483",
        "-1456680780",
        "491824726",
        "2137211747",
        "-1358769180"
      ]
    },
    {
      "hc_lt_id_alb": "-824026795",
      "hc_lt_id_nortag": "-1662551372",
      "hc_lt_id_sptag": "1782799997",
      "id_img": "KantaiCollection_792972_crop2608_-1203837549",
      "link_img": "UTb0sGqADnbLiHq9qhRMRkSRiLND0Tk7ctN8tpraiifky+UxKwLYnvyk5FEq2lEw9SsWF1oCkTBhTi/LzigROJVy4706IhQgSYlgwrgVRHU=",
      "thumb": "UTb0sGqADnbLiHq9qhRMRkSRiLND0Tk7ctN8tpraiifky+UxKwLYnvyk5FEq2lEweR4g5CJjmvLnFdR8MupfpZVy4706IhQgSYlgwrgVRHU=",
      "lt_id_alb": [
        "63410260"
      ],
      "list_id_nortag": [
        "579558099",
        "-1182628656"
      ],
      "lt_id_sptag": [
        "1545739930",
        "-678792093",
        "-1372583199",
        "750914149",
        "-1230434216",
        "473789866",
        "1945436082",
        "-667683750",
        "-353024394",
        "-1068725006",
        "1367612750",
        "1813151526",
        "-1152882625",
        "1078827483",
        "-1456680780",
        "-1042073588"
      ]
    },
    {
      "hc_lt_id_alb": "-824026795",
      "hc_lt_id_nortag": "-1442593610",
      "hc_lt_id_sptag": "-647481947",
      "id_img": "TokyoGhoul_596827_crop2608_-1411001379",
      "link_img": "UTb0sGqADnbLiHq9qhRMRkSRiLND0Tk7ctN8tpraiid80itteLAQrqEFSiUmDs369bjWtOsO9dwMqwR6CnQV3ZVy4706IhQgSYlgwrgVRHU=",
      "thumb": "UTb0sGqADnbLiHq9qhRMRkSRiLND0Tk7ctN8tpraiid80itteLAQrqEFSiUmDs36UVRX5DB6pqcRPm3QlV2wwpVy4706IhQgSYlgwrgVRHU=",
      "lt_id_alb": [
        "63410260"
      ],
      "list_id_nortag": [
        "-1182628656",
        "882178788"
      ],
      "lt_id_sptag": [
        "-1915687819",
        "-1239845591",
        "-1472410809",
        "-1216236529",
        "1166680991",
        "1367612750",
        "246776394",
        "680065126",
        "-2114154352",
        "579965105",
        "-1165766878",
        "1526533345",
        "1078827483",
        "491824726",
        "1410951528"
      ]
    },
    {
      "hc_lt_id_alb": "-824026795",
      "hc_lt_id_nortag": "-1532318063",
      "hc_lt_id_sptag": "7928397",
      "id_img": "SaekanoHowtoRaiseaBoringGirlfriend_679164_crop2608_59898483",
      "link_img": "UTb0sGqADnbLiHq9qhRMRkSRiLND0Tk7ctN8tpraiidCMZAMhDCYdWu9L5laX+dnpm3q+Ug9u1sSi7YYNe8wQ5Vy4706IhQgSYlgwrgVRHU=",
      "thumb": "UTb0sGqADnbLiHq9qhRMRkSRiLND0Tk7ctN8tpraiidCMZAMhDCYdWu9L5laX+dnd9bGVluymnU8JPsI91FuRZVy4706IhQgSYlgwrgVRHU=",
      "lt_id_alb": [
        "63410260"
      ],
      "list_id_nortag": [
        "1589031968",
        "-1182628656"
      ],
      "lt_id_sptag": [
        "-333189356",
        "1694271403",
        "1441067176",
        "29436897",
        "-353024394",
        "1367612750",
        "-1686571485",
        "1541647243",
        "424585427",
        "891036203",
        "-899599709",
        "1078827483",
        "2137211747",
        "-1602093195"
      ]
    },
    {
      "hc_lt_id_alb": "-824026795",
      "hc_lt_id_nortag": "-1114397356",
      "hc_lt_id_sptag": "41633344",
      "id_img": "Original_932406_crop2608_1683959746",
      "link_img": "UTb0sGqADnbLiHq9qhRMRkSRiLND0Tk7ctN8tpraiidSWjoaNuNUkfTXmIRb44a/QGrwf7glKekha39NXI3KH5Vy4706IhQgSYlgwrgVRHU=",
      "thumb": "UTb0sGqADnbLiHq9qhRMRkSRiLND0Tk7ctN8tpraiidSWjoaNuNUkfTXmIRb44a/WE5JpTx1KonV6AMxHjy8ZZVy4706IhQgSYlgwrgVRHU=",
      "lt_id_alb": [
        "63410260"
      ],
      "list_id_nortag": [
        "-669347768",
        "-1182628656"
      ],
      "lt_id_sptag": [
        "1271392973",
        "-1915687819",
        "-353024394",
        "-1092439432",
        "1367612750",
        "1913692055",
        "-414222762",
        "-1176638482",
        "-260062140",
        "-1823594757",
        "-2147125825",
        "1308072943",
        "-1882261033",
        "1078827483"
      ]
    },
    {
      "hc_lt_id_alb": "-824026795",
      "hc_lt_id_nortag": "832587751",
      "hc_lt_id_sptag": "137224467",
      "id_img": "Touhou_786639_crop2608_1901996452",
      "link_img": "UTb0sGqADnbLiHq9qhRMRkSRiLND0Tk7ctN8tpraiifbqy1S7Dcaajqsjl66LO36Yu9qmkcxYakfiieh/WXejpVy4706IhQgSYlgwrgVRHU=",
      "thumb": "UTb0sGqADnbLiHq9qhRMRkSRiLND0Tk7ctN8tpraiifbqy1S7Dcaajqsjl66LO36WHB6FR+J3nmYwjq8bZAmpJVy4706IhQgSYlgwrgVRHU=",
      "lt_id_alb": [
        "63410260"
      ],
      "list_id_nortag": [
        "-1182628656",
        "-843208019"
      ],
      "lt_id_sptag": [
        "750914149",
        "-1230434216",
        "1367612750",
        "376240968",
        "-1165766878",
        "1078827483",
        "2137211747",
        "1857376909",
        "1410951528"
      ]
    },
    {
      "hc_lt_id_alb": "-824026795",
      "hc_lt_id_nortag": "-416269392",
      "hc_lt_id_sptag": "1269670546",
      "id_img": "BokuWaTomodachiGaSukunai_712284_crop2608_737032352",
      "link_img": "UTb0sGqADnbLiHq9qhRMRkSRiLND0Tk7ctN8tpraiieFFtosEyjYoac4ADmHKtpeBa1gJBOly1FpuAuKXj/MsZVy4706IhQgSYlgwrgVRHU=",
      "thumb": "UTb0sGqADnbLiHq9qhRMRkSRiLND0Tk7ctN8tpraiieFFtosEyjYoac4ADmHKtpecdzKLJeC8lrF07hHf7d5HpVy4706IhQgSYlgwrgVRHU=",
      "lt_id_alb": [
        "63410260"
      ],
      "list_id_nortag": [
        "-684396608",
        "-1182628656"
      ],
      "lt_id_sptag": [
        "-1038892260",
        "-1915687819",
        "-1230434216",
        "-353024394",
        "1367612750",
        "376240968",
        "1906474058",
        "1508952095",
        "-1165766878",
        "-1882261033",
        "1078827483",
        "-516908271",
        "491824726",
        "-1353313151",
        "2137211747",
        "904137049"
      ]
    },
    {
      "hc_lt_id_alb": "-824026795",
      "hc_lt_id_nortag": "-2092928010",
      "hc_lt_id_sptag": "2110918388",
      "id_img": "Original_907720_crop2608_1815498069",
      "link_img": "UTb0sGqADnbLiHq9qhRMRkSRiLND0Tk7ctN8tpraiifUrIVwrXbOoR7DpTCH1mZEcvWz6ZyrpGX2qltoYRUL+pVy4706IhQgSYlgwrgVRHU=",
      "thumb": "UTb0sGqADnbLiHq9qhRMRkSRiLND0Tk7ctN8tpraiifUrIVwrXbOoR7DpTCH1mZE73rP8D2LLQjWAF7jcYtc7JVy4706IhQgSYlgwrgVRHU=",
      "lt_id_alb": [
        "63410260"
      ],
      "list_id_nortag": [
        "-1182628656",
        "-1556851449"
      ],
      "lt_id_sptag": [
        "-1230434216",
        "-353024394",
        "1367612750",
        "376240968",
        "-67611207",
        "-1450260536",
        "1541647243",
        "1078827483"
      ]
    },
    {
      "hc_lt_id_alb": "-824026795",
      "hc_lt_id_nortag": "832587751",
      "hc_lt_id_sptag": "846924305",
      "id_img": "Touhou_677592_crop2608_73744661",
      "link_img": "UTb0sGqADnbLiHq9qhRMRkSRiLND0Tk7ctN8tpraiifXFglXKu1/zjuyxoUodWYEm78WqwCVK3FLtj7rbsdXnJVy4706IhQgSYlgwrgVRHU=",
      "thumb": "UTb0sGqADnbLiHq9qhRMRkSRiLND0Tk7ctN8tpraiifXFglXKu1/zjuyxoUodWYEYFI4HLVnD8seuYwyv35TbZVy4706IhQgSYlgwrgVRHU=",
      "lt_id_alb": [
        "63410260"
      ],
      "list_id_nortag": [
        "-1182628656",
        "-843208019"
      ],
      "lt_id_sptag": [
        "-333189356",
        "1367612750",
        "376240968",
        "-1882261033",
        "1078827483",
        "1857376909",
        "-1358769180"
      ]
    },
    {
      "hc_lt_id_alb": "-824026795",
      "hc_lt_id_nortag": "1471769326",
      "hc_lt_id_sptag": "100592111",
      "id_img": "Original_714494_crop2608_2112312733",
      "link_img": "UTb0sGqADnbLiHq9qhRMRkSRiLND0Tk7ctN8tpraiif/XsD8vauSHSCPA1i8L0Gs562VKzik+ioThRoCOg+nfpVy4706IhQgSYlgwrgVRHU=",
      "thumb": "UTb0sGqADnbLiHq9qhRMRkSRiLND0Tk7ctN8tpraiif/XsD8vauSHSCPA1i8L0GscVKwpTICjnAlFLVzEI+gE5Vy4706IhQgSYlgwrgVRHU=",
      "lt_id_alb": [
        "63410260"
      ],
      "list_id_nortag": [
        "-1638897763",
        "-1182628656"
      ],
      "lt_id_sptag": [
        "1545739930",
        "-1216236529",
        "-353024394",
        "1367612750",
        "680065126",
        "1813151526",
        "1320442351",
        "1078827483",
        "26918368",
        "-1602093195"
      ]
    },
    {
      "hc_lt_id_alb": "-824026795",
      "hc_lt_id_nortag": "1115203702",
      "hc_lt_id_sptag": "-1030564285",
      "id_img": "AngelBeats_771277_crop2608_-487604746",
      "link_img": "UTb0sGqADnbLiHq9qhRMRkSRiLND0Tk7ctN8tpraiicOcEFKOrEol8qcCIgUG/gUSKtT40gzh5rDC7kbP8nGmZVy4706IhQgSYlgwrgVRHU=",
      "thumb": "UTb0sGqADnbLiHq9qhRMRkSRiLND0Tk7ctN8tpraiicOcEFKOrEol8qcCIgUG/gUWuFf1ZbKqcmnVsTz6g8AN5Vy4706IhQgSYlgwrgVRHU=",
      "lt_id_alb": [
        "63410260"
      ],
      "list_id_nortag": [
        "-1485458249",
        "-1182628656"
      ],
      "lt_id_sptag": [
        "177416588",
        "-1230434216",
        "1443880616",
        "1755521698",
        "-353024394",
        "643795693",
        "1367612750",
        "-67611207",
        "1541647243",
        "-1995563546",
        "-1823594757",
        "-3839867",
        "1078827483",
        "26918368",
        "1410951528",
        "-247566452"
      ]
    },
    {
      "hc_lt_id_alb": "-824026795",
      "hc_lt_id_nortag": "-2092928010",
      "hc_lt_id_sptag": "-494915000",
      "id_img": "Original_908093_crop2608_884108617",
      "link_img": "UTb0sGqADnbLiHq9qhRMRkSRiLND0Tk7ctN8tpraiic4nkJU7hd5RR8JmD4ll5RaTJBJRh3M+LB6fP7vh6Y1PpVy4706IhQgSYlgwrgVRHU=",
      "thumb": "UTb0sGqADnbLiHq9qhRMRkSRiLND0Tk7ctN8tpraiic4nkJU7hd5RR8JmD4ll5RaHbB5e12mn4H6EoUf3M+gzZVy4706IhQgSYlgwrgVRHU=",
      "lt_id_alb": [
        "63410260"
      ],
      "list_id_nortag": [
        "-1182628656",
        "-1556851449"
      ],
      "lt_id_sptag": [
        "937579079",
        "117222074",
        "-353024394",
        "1367612750",
        "376240968",
        "1913692055",
        "1813151526",
        "-260062140",
        "1078827483",
        "176756002"
      ]
    },
    {
      "hc_lt_id_alb": "-824026795",
      "hc_lt_id_nortag": "585558204",
      "hc_lt_id_sptag": "1056371191",
      "id_img": "ReZEROStartingLifeinAnotherWorld_723513_crop2608_-890154907",
      "link_img": "UTb0sGqADnbLiHq9qhRMRkSRiLND0Tk7ctN8tpraiicgUk9ewKOvj8QrMZ1B1x8DnCk4Ohedt2bnnX71SkupfJVy4706IhQgSYlgwrgVRHU=",
      "thumb": "UTb0sGqADnbLiHq9qhRMRkSRiLND0Tk7ctN8tpraiicgUk9ewKOvj8QrMZ1B1x8DoHpAIEkhX7ClnP3wsOmvSpVy4706IhQgSYlgwrgVRHU=",
      "lt_id_alb": [
        "63410260"
      ],
      "list_id_nortag": [
        "-1182628656",
        "-274114340"
      ],
      "lt_id_sptag": [
        "1010924017",
        "-1937610099",
        "1367612750",
        "246776394",
        "376240968",
        "-1450260536",
        "579965105",
        "-1882261033",
        "1526533345",
        "-1331370225",
        "-172225030",
        "1078827483",
        "26918368",
        "1410951528"
      ]
    },
    {
      "hc_lt_id_alb": "-824026795",
      "hc_lt_id_nortag": "-962447637",
      "hc_lt_id_sptag": "-1263038096",
      "id_img": "PuellaMagiMadokaMagica_677466_crop2608_1416194223",
      "link_img": "UTb0sGqADnbLiHq9qhRMRkSRiLND0Tk7ctN8tpraiif+Ekhbo7+IfD9zic0LOCkp67NuCUVhpcRS1VFuKwNjfZVy4706IhQgSYlgwrgVRHU=",
      "thumb": "UTb0sGqADnbLiHq9qhRMRkSRiLND0Tk7ctN8tpraiif+Ekhbo7+IfD9zic0LOCkpIFufrWG6lddTDAToEdWJUJVy4706IhQgSYlgwrgVRHU=",
      "lt_id_alb": [
        "63410260"
      ],
      "list_id_nortag": [
        "-1823434899",
        "-1182628656"
      ],
      "lt_id_sptag": [
        "-1038892260",
        "641041541",
        "1545739930",
        "866423119",
        "1037188654",
        "1755521698",
        "-353024394",
        "1367612750",
        "-1686571485",
        "63311442",
        "-1353196196",
        "-1307705100",
        "-1277319363",
        "-3839867",
        "1677155011",
        "1078827483",
        "-1456680780",
        "-1353313151"
      ]
    },
    {
      "hc_lt_id_alb": "-824026795",
      "hc_lt_id_nortag": "-1900683268",
      "hc_lt_id_sptag": "582551093",
      "id_img": "FairyTail_918536_crop2608_-873163932",
      "link_img": "UTb0sGqADnbLiHq9qhRMRkSRiLND0Tk7ctN8tpraiif9YmjbzD5bu21t0VwEWZHVUBeIoMdn+31xGCP3CXiUN5Vy4706IhQgSYlgwrgVRHU=",
      "thumb": "UTb0sGqADnbLiHq9qhRMRkSRiLND0Tk7ctN8tpraiif9YmjbzD5bu21t0VwEWZHVMX+U/keLvpCBj5GRwoj+NpVy4706IhQgSYlgwrgVRHU=",
      "lt_id_alb": [
        "63410260"
      ],
      "list_id_nortag": [
        "-1250415468",
        "-1182628656"
      ],
      "lt_id_sptag": [
        "1545739930",
        "-333189356",
        "-1230434216",
        "1717628584",
        "-353024394",
        "1367612750",
        "-1686571485",
        "-67611207",
        "-1208878804",
        "1078827483"
      ]
    },
    {
      "hc_lt_id_alb": "-824026795",
      "hc_lt_id_nortag": "-2092928010",
      "hc_lt_id_sptag": "-201683982",
      "id_img": "Original_907524_crop2608_844118615",
      "link_img": "UTb0sGqADnbLiHq9qhRMRkSRiLND0Tk7ctN8tpraiidjfmzJ6pH19+jhswcIUtmCyrdF2zcPYmPHLw0fmXfg1ZVy4706IhQgSYlgwrgVRHU=",
      "thumb": "UTb0sGqADnbLiHq9qhRMRkSRiLND0Tk7ctN8tpraiidjfmzJ6pH19+jhswcIUtmCMvQOgx+9W3+5HPJl73q+45Vy4706IhQgSYlgwrgVRHU=",
      "lt_id_alb": [
        "63410260"
      ],
      "list_id_nortag": [
        "-1182628656",
        "-1556851449"
      ],
      "lt_id_sptag": [
        "-1230434216",
        "-729883027",
        "-353024394",
        "1367612750",
        "1913692055",
        "1846426926",
        "-260062140",
        "-1165766878",
        "1078827483",
        "703590460",
        "2137211747",
        "1039377061"
      ]
    },
    {
      "hc_lt_id_alb": "-824026795",
      "hc_lt_id_nortag": "-1532318063",
      "hc_lt_id_sptag": "-836408357",
      "id_img": "SaekanoHowtoRaiseaBoringGirlfriend_679155_crop2608_-938779441",
      "link_img": "UTb0sGqADnbLiHq9qhRMRkSRiLND0Tk7ctN8tpraiidgtApqji1N/IDRkzdqjlQ73ngKEmTgOqiqxKJJmOxVXZVy4706IhQgSYlgwrgVRHU=",
      "thumb": "UTb0sGqADnbLiHq9qhRMRkSRiLND0Tk7ctN8tpraiidgtApqji1N/IDRkzdqjlQ745DalDfPLZghamu01FAw4pVy4706IhQgSYlgwrgVRHU=",
      "lt_id_alb": [
        "63410260"
      ],
      "list_id_nortag": [
        "1589031968",
        "-1182628656"
      ],
      "lt_id_sptag": [
        "-561045702",
        "-333189356",
        "1441067176",
        "-111108595",
        "29436897",
        "117222074",
        "1367612750",
        "-1686571485",
        "1541647243",
        "1846426926",
        "1813151526",
        "1078827483",
        "1410951528"
      ]
    },
    {
      "hc_lt_id_alb": "-824026795",
      "hc_lt_id_nortag": "-1662551372",
      "hc_lt_id_sptag": "-275659974",
      "id_img": "KantaiCollection_705490_crop2608_1192406366",
      "link_img": "UTb0sGqADnbLiHq9qhRMRkSRiLND0Tk7ctN8tpraiidt97qRY//STP+9kAnKgLBSF72eGTCiuDCYUhUYGDYKBZVy4706IhQgSYlgwrgVRHU=",
      "thumb": "UTb0sGqADnbLiHq9qhRMRkSRiLND0Tk7ctN8tpraiidt97qRY//STP+9kAnKgLBSF74/GheoVsCnd8WHoqwLlZVy4706IhQgSYlgwrgVRHU=",
      "lt_id_alb": [
        "63410260"
      ],
      "list_id_nortag": [
        "579558099",
        "-1182628656"
      ],
      "lt_id_sptag": [
        "-1038892260",
        "-1915687819",
        "177416588",
        "-1372583199",
        "-1937610099",
        "473789866",
        "1755521698",
        "489705754",
        "1945436082",
        "-667683750",
        "-353024394",
        "1367612750",
        "-1686571485",
        "-1152882625",
        "-260062140",
        "-3839867",
        "1078827483",
        "-1456680780",
        "-1042073588",
        "26918368",
        "1410951528"
      ]
    },
    {
      "hc_lt_id_alb": "-824026795",
      "hc_lt_id_nortag": "-1662551372",
      "hc_lt_id_sptag": "628794462",
      "id_img": "KantaiCollection_705490_crop2608_1849972401",
      "link_img": "UTb0sGqADnbLiHq9qhRMRkSRiLND0Tk7ctN8tpraiidUTbVUoi7ne+TtuKcVWAirJsErQxeqIvtEA1O2F4gX7pVy4706IhQgSYlgwrgVRHU=",
      "thumb": "UTb0sGqADnbLiHq9qhRMRkSRiLND0Tk7ctN8tpraiidUTbVUoi7ne+TtuKcVWAirPWXATUaLEMizIGVusKRTZJVy4706IhQgSYlgwrgVRHU=",
      "lt_id_alb": [
        "63410260"
      ],
      "list_id_nortag": [
        "579558099",
        "-1182628656"
      ],
      "lt_id_sptag": [
        "-1038892260",
        "177416588",
        "-1372583199",
        "-1937610099",
        "473789866",
        "1755521698",
        "489705754",
        "1945436082",
        "-667683750",
        "-353024394",
        "1367612750",
        "-1152882625",
        "-260062140",
        "-3839867",
        "1078827483",
        "-1456680780",
        "-1042073588",
        "26918368"
      ]
    },
    {
      "hc_lt_id_alb": "-824026795",
      "hc_lt_id_nortag": "832587751",
      "hc_lt_id_sptag": "-595252132",
      "id_img": "Touhou_217833_crop2608_-1773310435",
      "link_img": "UTb0sGqADnbLiHq9qhRMRkSRiLND0Tk7ctN8tpraiie9OoA0/0RBlt3FyoiWo+knckFKxKMe6EzHtE2u3OWas5Vy4706IhQgSYlgwrgVRHU=",
      "thumb": "UTb0sGqADnbLiHq9qhRMRkSRiLND0Tk7ctN8tpraiie9OoA0/0RBlt3FyoiWo+knBdD0UbJQpzTuKO0qrN/XFZVy4706IhQgSYlgwrgVRHU=",
      "lt_id_alb": [
        "63410260"
      ],
      "list_id_nortag": [
        "-1182628656",
        "-843208019"
      ],
      "lt_id_sptag": [
        "218089402",
        "1367612750",
        "376240968",
        "-1165766878",
        "-1882261033",
        "1078827483",
        "2137211747",
        "1857376909",
        "26918368",
        "1410951528",
        "176756002"
      ]
    },
    {
      "hc_lt_id_alb": "-824026795",
      "hc_lt_id_nortag": "-2092928010",
      "hc_lt_id_sptag": "1665612207",
      "id_img": "Original_907516_crop2608_74789114",
      "link_img": "UTb0sGqADnbLiHq9qhRMRkSRiLND0Tk7ctN8tpraiifrKxH3h4BO4d/pO6ReorUsRZC1etv7jvs+BGVgx11syJVy4706IhQgSYlgwrgVRHU=",
      "thumb": "UTb0sGqADnbLiHq9qhRMRkSRiLND0Tk7ctN8tpraiifrKxH3h4BO4d/pO6ReorUs0IPoixkUXFRlxDnktBC1EZVy4706IhQgSYlgwrgVRHU=",
      "lt_id_alb": [
        "63410260"
      ],
      "list_id_nortag": [
        "-1182628656",
        "-1556851449"
      ],
      "lt_id_sptag": [
        "1090937228",
        "1545739930",
        "-333189356",
        "750914149",
        "-1230434216",
        "1367612750",
        "-1686571485",
        "2043573436",
        "1078827483",
        "-1980983817",
        "1410951528"
      ]
    },
    {
      "hc_lt_id_alb": "-824026795",
      "hc_lt_id_nortag": "-962447637",
      "hc_lt_id_sptag": "-992598463",
      "id_img": "PuellaMagiMadokaMagica_226728_crop2608_1600922106",
      "link_img": "UTb0sGqADnbLiHq9qhRMRkSRiLND0Tk7ctN8tpraiiemcMHeq8BBHVyTiOjP0k17lbfR5zav2JOV1cCyHly0n5Vy4706IhQgSYlgwrgVRHU=",
      "thumb": "UTb0sGqADnbLiHq9qhRMRkSRiLND0Tk7ctN8tpraiiemcMHeq8BBHVyTiOjP0k17zjUSuzRxVOr+A6fZMJKocZVy4706IhQgSYlgwrgVRHU=",
      "lt_id_alb": [
        "63410260"
      ],
      "list_id_nortag": [
        "-1823434899",
        "-1182628656"
      ],
      "lt_id_sptag": [
        "641041541",
        "1545739930",
        "-1216236529",
        "1037188654",
        "-2024578405",
        "1367612750",
        "-1866523531",
        "-67611207",
        "680065126",
        "1089393616",
        "-1165766878",
        "-1455727370",
        "1078827483",
        "-1456680780",
        "491824726",
        "-343568313",
        "2137211747",
        "1410951528"
      ]
    },
    {
      "hc_lt_id_alb": "-824026795",
      "hc_lt_id_nortag": "-1114397356",
      "hc_lt_id_sptag": "1445769984",
      "id_img": "Original_914300_crop2608_-2021894021",
      "link_img": "UTb0sGqADnbLiHq9qhRMRkSRiLND0Tk7ctN8tpraiifEZZ7XBIIgsiI7Y+6Io7TylaA6r5QtUEK0tXXQ988+LpVy4706IhQgSYlgwrgVRHU=",
      "thumb": "UTb0sGqADnbLiHq9qhRMRkSRiLND0Tk7ctN8tpraiifEZZ7XBIIgsiI7Y+6Io7Ty8ZMYvbbqzUaGaLBME+O03JVy4706IhQgSYlgwrgVRHU=",
      "lt_id_alb": [
        "63410260"
      ],
      "list_id_nortag": [
        "-669347768",
        "-1182628656"
      ],
      "lt_id_sptag": [
        "1545739930",
        "-1216236529",
        "-353024394",
        "643795693",
        "1367612750",
        "246776394",
        "1541647243",
        "680065126",
        "1526533345",
        "1078827483",
        "-1085357263"
      ]
    },
    {
      "hc_lt_id_alb": "-824026795",
      "hc_lt_id_nortag": "-100972981",
      "hc_lt_id_sptag": "-1122953984",
      "id_img": "Noragami_678561_crop2608_1738951588",
      "link_img": "UTb0sGqADnbLiHq9qhRMRkSRiLND0Tk7ctN8tpraiieLKXNwYGWChDCKgWK35O+MjOpt3fFYfcUa/HgnZtvtqpVy4706IhQgSYlgwrgVRHU=",
      "thumb": "UTb0sGqADnbLiHq9qhRMRkSRiLND0Tk7ctN8tpraiieLKXNwYGWChDCKgWK35O+Mv8HP0+Z73JX9aBLduxnhIJVy4706IhQgSYlgwrgVRHU=",
      "lt_id_alb": [
        "63410260"
      ],
      "list_id_nortag": [
        "402664479",
        "-1182628656"
      ],
      "lt_id_sptag": [
        "-1915687819",
        "1791116166",
        "-1669187985",
        "1367612750",
        "-1686571485",
        "1078827483",
        "1410951528",
        "225940197"
      ]
    },
    {
      "hc_lt_id_alb": "-824026795",
      "hc_lt_id_nortag": "-1971765911",
      "hc_lt_id_sptag": "1632735014",
      "id_img": "OnePiece_932968_crop2608_745588620",
      "link_img": "UTb0sGqADnbLiHq9qhRMRkSRiLND0Tk7ctN8tpraiieF8I5SLH9jV15Gv1whggELNeNE45ZSL8w68/3liNuXSpVy4706IhQgSYlgwrgVRHU=",
      "thumb": "UTb0sGqADnbLiHq9qhRMRkSRiLND0Tk7ctN8tpraiieF8I5SLH9jV15Gv1whggELDP6hpJCvpUzd93Y63hfqO5Vy4706IhQgSYlgwrgVRHU=",
      "lt_id_alb": [
        "63410260"
      ],
      "list_id_nortag": [
        "-1166409139",
        "-467032699"
      ],
      "lt_id_sptag": [
        "1367612750",
        "-1455727370",
        "1428433125"
      ]
    },
    {
      "hc_lt_id_alb": "-824026795",
      "hc_lt_id_nortag": "-822968574",
      "hc_lt_id_sptag": "-675470866",
      "id_img": "MissKobayashisDragonMaid_881183_crop2608_-568354185",
      "link_img": "UTb0sGqADnbLiHq9qhRMRkSRiLND0Tk7ctN8tpraiicQSpPWHteVmDTCPJ9A23Hp8vAzGKm11tvJzBNzrrXtO5Vy4706IhQgSYlgwrgVRHU=",
      "thumb": "UTb0sGqADnbLiHq9qhRMRkSRiLND0Tk7ctN8tpraiicQSpPWHteVmDTCPJ9A23HpWAB0jjqYlv1y4vtv3mgc8ZVy4706IhQgSYlgwrgVRHU=",
      "lt_id_alb": [
        "63410260"
      ],
      "list_id_nortag": [
        "807641379",
        "-1182628656"
      ],
      "lt_id_sptag": [
        "-2017515920",
        "702196920",
        "-1130112717",
        "1010924017",
        "-375059391",
        "606716576",
        "-1230434216",
        "1755521698",
        "-353024394",
        "1367612750",
        "63311442",
        "-67611207",
        "886532079",
        "1089393616",
        "-1165766878",
        "-1025861007",
        "1078827483",
        "-1456680780",
        "2137211747"
      ]
    },
    {
      "hc_lt_id_alb": "-824026795",
      "hc_lt_id_nortag": "-1131068287",
      "hc_lt_id_sptag": "-58333148",
      "id_img": "Original_956376_crop2608_-330387752",
      "link_img": "UTb0sGqADnbLiHq9qhRMRkSRiLND0Tk7ctN8tpraiieNtwb0/kp9wprrqteMjuqfk4n/WAGxClWXgSjbgWty2JVy4706IhQgSYlgwrgVRHU=",
      "thumb": "UTb0sGqADnbLiHq9qhRMRkSRiLND0Tk7ctN8tpraiieNtwb0/kp9wprrqteMjuqfxM4KEjpqFHFe7p0PTtZWrpVy4706IhQgSYlgwrgVRHU=",
      "lt_id_alb": [
        "63410260"
      ],
      "list_id_nortag": [
        "-1182628656"
      ],
      "lt_id_sptag": [
        "1545739930",
        "-1937610099",
        "-353024394",
        "1367612750",
        "376240968",
        "1913692055",
        "1768110807",
        "-1165766878",
        "-1823594757",
        "-1882261033",
        "1078827483",
        "2137211747"
      ]
    },
    {
      "hc_lt_id_alb": "-824026795",
      "hc_lt_id_nortag": "832587751",
      "hc_lt_id_sptag": "-595252132",
      "id_img": "Touhou_217833_crop2608_-125566315",
      "link_img": "UTb0sGqADnbLiHq9qhRMRkSRiLND0Tk7ctN8tpraiidE7+GQrE/c2emjaPsb6JbxIUbCSihtUxNe9IhchPtqHZVy4706IhQgSYlgwrgVRHU=",
      "thumb": "UTb0sGqADnbLiHq9qhRMRkSRiLND0Tk7ctN8tpraiidE7+GQrE/c2emjaPsb6JbxzHhjQKjeq08W2qrMEPfaXJVy4706IhQgSYlgwrgVRHU=",
      "lt_id_alb": [
        "63410260"
      ],
      "list_id_nortag": [
        "-1182628656",
        "-843208019"
      ],
      "lt_id_sptag": [
        "218089402",
        "1367612750",
        "376240968",
        "-1165766878",
        "-1882261033",
        "1078827483",
        "2137211747",
        "1857376909",
        "26918368",
        "1410951528",
        "176756002"
      ]
    },
    {
      "hc_lt_id_alb": "-824026795",
      "hc_lt_id_nortag": "-1662551372",
      "hc_lt_id_sptag": "-377064116",
      "id_img": "KantaiCollection_705490_crop2608_-999729356",
      "link_img": "UTb0sGqADnbLiHq9qhRMRkSRiLND0Tk7ctN8tpraiifY26PICVUHhVucNJ/615mWMukGGyxUghmJhjmJzTbVmZVy4706IhQgSYlgwrgVRHU=",
      "thumb": "UTb0sGqADnbLiHq9qhRMRkSRiLND0Tk7ctN8tpraiifY26PICVUHhVucNJ/615mWZE16gna41wve2jS1KUmjiZVy4706IhQgSYlgwrgVRHU=",
      "lt_id_alb": [
        "63410260"
      ],
      "list_id_nortag": [
        "579558099",
        "-1182628656"
      ],
      "lt_id_sptag": [
        "-1038892260",
        "-1915687819",
        "177416588",
        "-1372583199",
        "-1937610099",
        "473789866",
        "489705754",
        "1945436082",
        "-667683750",
        "-353024394",
        "1367612750",
        "376240968",
        "-1686571485",
        "-1152882625",
        "-260062140",
        "-3839867",
        "1078827483",
        "-1456680780",
        "-1042073588",
        "26918368",
        "1410951528"
      ]
    },
    {
      "hc_lt_id_alb": "-824026795",
      "hc_lt_id_nortag": "1229705628",
      "hc_lt_id_sptag": "-30475071",
      "id_img": "AvatarTheLegendOfKorra_556517_crop2608_124728277",
      "link_img": "UTb0sGqADnbLiHq9qhRMRkSRiLND0Tk7ctN8tpraiidfG3NPVCFqN04PeEYNzAEcn5pTA9tdW44qh+MXpqjbrpVy4706IhQgSYlgwrgVRHU=",
      "thumb": "UTb0sGqADnbLiHq9qhRMRkSRiLND0Tk7ctN8tpraiidfG3NPVCFqN04PeEYNzAEcU086F0ltjOvIoc13/+GAvJVy4706IhQgSYlgwrgVRHU=",
      "lt_id_alb": [
        "63410260"
      ],
      "list_id_nortag": [
        "-1494515094"
      ],
      "lt_id_sptag": [
        "-1612212205",
        "148046112",
        "1367612750",
        "-1455727370"
      ]
    },
    {
      "hc_lt_id_alb": "-824026795",
      "hc_lt_id_nortag": "-2092928010",
      "hc_lt_id_sptag": "-325302171",
      "id_img": "Original_907765_crop2608_-1278814186",
      "link_img": "UTb0sGqADnbLiHq9qhRMRkSRiLND0Tk7ctN8tpraiiemCr87EWubkQSiG6E3HCjV1Kw0ONSqNmCMvR29rdAi1ZVy4706IhQgSYlgwrgVRHU=",
      "thumb": "UTb0sGqADnbLiHq9qhRMRkSRiLND0Tk7ctN8tpraiiemCr87EWubkQSiG6E3HCjVgptiN7jCusSs6nOzd3800ZVy4706IhQgSYlgwrgVRHU=",
      "lt_id_alb": [
        "63410260"
      ],
      "list_id_nortag": [
        "-1182628656",
        "-1556851449"
      ],
      "lt_id_sptag": [
        "1552857583",
        "750914149",
        "-1230434216",
        "-353024394",
        "1367612750",
        "376240968",
        "-1686571485",
        "1078827483",
        "-1456680780",
        "491824726"
      ]
    },
    {
      "hc_lt_id_alb": "-824026795",
      "hc_lt_id_nortag": "322817577",
      "hc_lt_id_sptag": "1124897528",
      "id_img": "DagashiKashi_677967_crop2608_366768948",
      "link_img": "UTb0sGqADnbLiHq9qhRMRkSRiLND0Tk7ctN8tpraiic07Hel1guQyVOTqP/ibHhYM2whkE2XydSBMzXUpq6XYJVy4706IhQgSYlgwrgVRHU=",
      "thumb": "UTb0sGqADnbLiHq9qhRMRkSRiLND0Tk7ctN8tpraiic07Hel1guQyVOTqP/ibHhYc++zcK5AfkShcLxSseN9O5Vy4706IhQgSYlgwrgVRHU=",
      "lt_id_alb": [
        "63410260"
      ],
      "list_id_nortag": [
        "1095644500",
        "-1182628656"
      ],
      "lt_id_sptag": [
        "-1230434216",
        "643795693",
        "1367612750",
        "376240968",
        "-260062140",
        "1078827483",
        "-660511924",
        "1410951528"
      ]
    },
    {
      "hc_lt_id_alb": "-824026795",
      "hc_lt_id_nortag": "832587751",
      "hc_lt_id_sptag": "-612439766",
      "id_img": "Touhou_914748_crop2608_-264915076",
      "link_img": "UTb0sGqADnbLiHq9qhRMRkSRiLND0Tk7ctN8tpraiifSNCbwMHCVcGWhiB+IXFmRljHeIbbRzWroRjExU9AC3pVy4706IhQgSYlgwrgVRHU=",
      "thumb": "UTb0sGqADnbLiHq9qhRMRkSRiLND0Tk7ctN8tpraiifSNCbwMHCVcGWhiB+IXFmRIrqSchcB3g0vwsXMu6lStJVy4706IhQgSYlgwrgVRHU=",
      "lt_id_alb": [
        "63410260"
      ],
      "list_id_nortag": [
        "-1182628656",
        "-843208019"
      ],
      "lt_id_sptag": [
        "-1230434216",
        "-464433724",
        "1367612750",
        "376240968",
        "-1165766878",
        "-1882261033",
        "1078827483",
        "2137211747",
        "1857376909",
        "1410951528"
      ]
    },
    {
      "hc_lt_id_alb": "-824026795",
      "hc_lt_id_nortag": "-1532318063",
      "hc_lt_id_sptag": "506148854",
      "id_img": "SaekanoHowtoRaiseaBoringGirlfriend_679164_crop2608_-318868993",
      "link_img": "UTb0sGqADnbLiHq9qhRMRkSRiLND0Tk7ctN8tpraiidts7R8jwvOZvDoMFv3T+7dzUEHFUIWWUthRvlCGclSDpVy4706IhQgSYlgwrgVRHU=",
      "thumb": "UTb0sGqADnbLiHq9qhRMRkSRiLND0Tk7ctN8tpraiidts7R8jwvOZvDoMFv3T+7dq3/zhqdSTqETmryyAazl/5Vy4706IhQgSYlgwrgVRHU=",
      "lt_id_alb": [
        "63410260"
      ],
      "list_id_nortag": [
        "1589031968",
        "-1182628656"
      ],
      "lt_id_sptag": [
        "-1915687819",
        "-333189356",
        "1694271403",
        "1441067176",
        "29436897",
        "-353024394",
        "1367612750",
        "-1686571485",
        "1541647243",
        "424585427",
        "1813151526",
        "891036203",
        "1078827483",
        "2137211747",
        "-1602093195"
      ]
    },
    {
      "hc_lt_id_alb": "-824026795",
      "hc_lt_id_nortag": "-822968574",
      "hc_lt_id_sptag": "603370138",
      "id_img": "MissKobayashisDragonMaid_881169_crop2608_-2060658324",
      "link_img": "UTb0sGqADnbLiHq9qhRMRkSRiLND0Tk7ctN8tpraiidvSH8nM3+iDggl3uMgGZabzaal9FlA/7WoRrE6LETN8pVy4706IhQgSYlgwrgVRHU=",
      "thumb": "UTb0sGqADnbLiHq9qhRMRkSRiLND0Tk7ctN8tpraiidvSH8nM3+iDggl3uMgGZabXUTfVmLkD9QJWMaH3ZJqv5Vy4706IhQgSYlgwrgVRHU=",
      "lt_id_alb": [
        "63410260"
      ],
      "list_id_nortag": [
        "807641379",
        "-1182628656"
      ],
      "lt_id_sptag": [
        "-1216236529",
        "606716576",
        "-353024394",
        "538504409",
        "1367612750",
        "376240968",
        "-67611207",
        "680065126",
        "886532079",
        "-1823594757",
        "1078827483",
        "-1456680780",
        "-1358769180"
      ]
    },
    {
      "hc_lt_id_alb": "-824026795",
      "hc_lt_id_nortag": "-739215050",
      "hc_lt_id_sptag": "-59102901",
      "id_img": "TokyoGhoul_596868_crop2608_-1945586278",
      "link_img": "UTb0sGqADnbLiHq9qhRMRkSRiLND0Tk7ctN8tpraiietIQbF3kOuPaBAjJMBE+p2mX1kxj53MjBScN54aBqlpZVy4706IhQgSYlgwrgVRHU=",
      "thumb": "UTb0sGqADnbLiHq9qhRMRkSRiLND0Tk7ctN8tpraiietIQbF3kOuPaBAjJMBE+p2cusUmGZkHMwC73VqWt7IepVy4706IhQgSYlgwrgVRHU=",
      "lt_id_alb": [
        "63410260"
      ],
      "list_id_nortag": [
        "882178788"
      ],
      "lt_id_sptag": [
        "177416588",
        "-1239845591",
        "-1491861316",
        "-42452310",
        "1367612750",
        "-1307705100",
        "1171821264",
        "-1730597006",
        "-2046828957",
        "1623277449"
      ]
    },
    {
      "hc_lt_id_alb": "-824026795",
      "hc_lt_id_nortag": "-1442593610",
      "hc_lt_id_sptag": "-331848352",
      "id_img": "TokyoGhoul_917511_crop2608_-1292366840",
      "link_img": "UTb0sGqADnbLiHq9qhRMRkSRiLND0Tk7ctN8tpraiid4lcZOdPWYwgQrgCEbGzdUZ+OBnylGhvx6CTGg6VQzbZVy4706IhQgSYlgwrgVRHU=",
      "thumb": "UTb0sGqADnbLiHq9qhRMRkSRiLND0Tk7ctN8tpraiid4lcZOdPWYwgQrgCEbGzdUltu+8sXaM+xGJr2FL4hehZVy4706IhQgSYlgwrgVRHU=",
      "lt_id_alb": [
        "63410260"
      ],
      "list_id_nortag": [
        "-1182628656",
        "882178788"
      ],
      "lt_id_sptag": [
        "-1239845591",
        "1367612750",
        "-67611207",
        "1722132917",
        "1813151526",
        "1447453426",
        "1078827483",
        "491824726",
        "-1903341030",
        "1410951528"
      ]
    },
    {
      "hc_lt_id_alb": "-824026795",
      "hc_lt_id_nortag": "1471769326",
      "hc_lt_id_sptag": "378977928",
      "id_img": "Original_713194_crop2608_113573875",
      "link_img": "UTb0sGqADnbLiHq9qhRMRkSRiLND0Tk7ctN8tpraiidCa4ojwClijpJJrr5DPA0GEDRhC3Yhc4is4eZkquiNnpVy4706IhQgSYlgwrgVRHU=",
      "thumb": "UTb0sGqADnbLiHq9qhRMRkSRiLND0Tk7ctN8tpraiidCa4ojwClijpJJrr5DPA0GVDb8uELeQESglnwDa5Y1RJVy4706IhQgSYlgwrgVRHU=",
      "lt_id_alb": [
        "63410260"
      ],
      "list_id_nortag": [
        "-1638897763",
        "-1182628656"
      ],
      "lt_id_sptag": [
        "1004491673",
        "-124333362",
        "1124215239",
        "1367612750",
        "376240968",
        "-67611207",
        "1168591711",
        "1846426926",
        "-1823594757",
        "-69431816",
        "1078827483",
        "491824726",
        "1410951528"
      ]
    },
    {
      "hc_lt_id_alb": "-824026795",
      "hc_lt_id_nortag": "-1850314428",
      "hc_lt_id_sptag": "-1643575618",
      "id_img": "DateALive_519517_crop2608_356679006",
      "link_img": "UTb0sGqADnbLiHq9qhRMRkSRiLND0Tk7ctN8tpraiictweGD80vTRMZ8/+7ybHhPkITJ0yyCNXX2RJz1mUDb/ZVy4706IhQgSYlgwrgVRHU=",
      "thumb": "UTb0sGqADnbLiHq9qhRMRkSRiLND0Tk7ctN8tpraiictweGD80vTRMZ8/+7ybHhPIztXsU/spathzLBFHGBoyJVy4706IhQgSYlgwrgVRHU=",
      "lt_id_alb": [
        "63410260"
      ],
      "list_id_nortag": [
        "-806183626",
        "-1182628656"
      ],
      "lt_id_sptag": [
        "1613046064",
        "-220048903",
        "1755521698",
        "-353024394",
        "-1092439432",
        "1367612750",
        "-1686571485",
        "-1176638482",
        "-260062140",
        "-1961656491",
        "1078827483"
      ]
    },
    {
      "hc_lt_id_alb": "-824026795",
      "hc_lt_id_nortag": "-1114397356",
      "hc_lt_id_sptag": "-837544141",
      "id_img": "Original_925106_crop2608_793747182",
      "link_img": "UTb0sGqADnbLiHq9qhRMRkSRiLND0Tk7ctN8tpraiicQnDFYpNqrgrPBaWFoSSrayVWevtoNLtqiwJYUut3repVy4706IhQgSYlgwrgVRHU=",
      "thumb": "UTb0sGqADnbLiHq9qhRMRkSRiLND0Tk7ctN8tpraiicQnDFYpNqrgrPBaWFoSSraaRvK5lerMYlhau/MvAHNrpVy4706IhQgSYlgwrgVRHU=",
      "lt_id_alb": [
        "63410260"
      ],
      "list_id_nortag": [
        "-669347768",
        "-1182628656"
      ],
      "lt_id_sptag": [
        "1367612750",
        "376240968",
        "-1686571485",
        "2026891902",
        "1078827483",
        "1410951528"
      ]
    },
    {
      "hc_lt_id_alb": "-824026795",
      "hc_lt_id_nortag": "832587751",
      "hc_lt_id_sptag": "-612439766",
      "id_img": "Touhou_914748_crop2608_-2016571050",
      "link_img": "UTb0sGqADnbLiHq9qhRMRkSRiLND0Tk7ctN8tpraiic0GE8SPA4iClD3z9VMEZk7D91BAJV+hrL9iYrScCBntJVy4706IhQgSYlgwrgVRHU=",
      "thumb": "UTb0sGqADnbLiHq9qhRMRkSRiLND0Tk7ctN8tpraiic0GE8SPA4iClD3z9VMEZk7Os9v7AhUH+bNu7jdndsYQJVy4706IhQgSYlgwrgVRHU=",
      "lt_id_alb": [
        "63410260"
      ],
      "list_id_nortag": [
        "-1182628656",
        "-843208019"
      ],
      "lt_id_sptag": [
        "-1230434216",
        "-464433724",
        "1367612750",
        "376240968",
        "-1165766878",
        "-1882261033",
        "1078827483",
        "2137211747",
        "1857376909",
        "1410951528"
      ]
    },
    {
      "hc_lt_id_alb": "-824026795",
      "hc_lt_id_nortag": "-324199368",
      "hc_lt_id_sptag": "-1986880141",
      "id_img": "Vocaloid_684742_crop2608_-579338433",
      "link_img": "UTb0sGqADnbLiHq9qhRMRkSRiLND0Tk7ctN8tpraiicCs90sk7IZuvDUVpmVvfcmba/nh1074WdLRE5IRJATFZVy4706IhQgSYlgwrgVRHU=",
      "thumb": "UTb0sGqADnbLiHq9qhRMRkSRiLND0Tk7ctN8tpraiicCs90sk7IZuvDUVpmVvfcmnmQGIykkAtogYei0nXBlWJVy4706IhQgSYlgwrgVRHU=",
      "lt_id_alb": [
        "63410260"
      ],
      "list_id_nortag": [
        "-324062098",
        "-1182628656"
      ],
      "lt_id_sptag": [
        "935793454",
        "-353024394",
        "1367612750",
        "376240968",
        "1627623413",
        "1078827483",
        "1457245087"
      ]
    },
    {
      "hc_lt_id_alb": "-824026795",
      "hc_lt_id_nortag": "-739215050",
      "hc_lt_id_sptag": "-59102901",
      "id_img": "TokyoGhoul_596868_crop2608_145971064",
      "link_img": "UTb0sGqADnbLiHq9qhRMRkSRiLND0Tk7ctN8tpraiieWD/i2IZQvFNsPibUyq+lb1zXgmveDxpipkDCg5iVDp5Vy4706IhQgSYlgwrgVRHU=",
      "thumb": "UTb0sGqADnbLiHq9qhRMRkSRiLND0Tk7ctN8tpraiieWD/i2IZQvFNsPibUyq+lbT9ulHFuDCRRFAwyzeIU3rpVy4706IhQgSYlgwrgVRHU=",
      "lt_id_alb": [
        "63410260"
      ],
      "list_id_nortag": [
        "882178788"
      ],
      "lt_id_sptag": [
        "177416588",
        "-1239845591",
        "-1491861316",
        "-42452310",
        "1367612750",
        "-1307705100",
        "1171821264",
        "-1730597006",
        "-2046828957",
        "1623277449"
      ]
    },
    {
      "hc_lt_id_alb": "-824026795",
      "hc_lt_id_nortag": "-1532318063",
      "hc_lt_id_sptag": "1207136288",
      "id_img": "SaekanoHowtoRaiseaBoringGirlfriend_679164_crop2608_-471150702",
      "link_img": "UTb0sGqADnbLiHq9qhRMRkSRiLND0Tk7ctN8tpraiieZUVMyJWacxkgYxINvV5sdsHGltfgeLCHJnwG9HMcb5ZVy4706IhQgSYlgwrgVRHU=",
      "thumb": "UTb0sGqADnbLiHq9qhRMRkSRiLND0Tk7ctN8tpraiieZUVMyJWacxkgYxINvV5sd25sLZK2I0O2l+P3sQ2fXIpVy4706IhQgSYlgwrgVRHU=",
      "lt_id_alb": [
        "63410260"
      ],
      "list_id_nortag": [
        "1589031968",
        "-1182628656"
      ],
      "lt_id_sptag": [
        "-333189356",
        "1694271403",
        "1441067176",
        "29436897",
        "-353024394",
        "1367612750",
        "376240968",
        "1541647243",
        "424585427",
        "-1165766878",
        "891036203",
        "1078827483",
        "2137211747",
        "-1602093195"
      ]
    },
    {
      "hc_lt_id_alb": "-824026795",
      "hc_lt_id_nortag": "-2092928010",
      "hc_lt_id_sptag": "-1859417508",
      "id_img": "Original_907801_crop2608_-23122087",
      "link_img": "UTb0sGqADnbLiHq9qhRMRkSRiLND0Tk7ctN8tpraiieAtUNCUH5eTv3YkL2lNVHUNfJRcz5S/EtVBma34g+eOpVy4706IhQgSYlgwrgVRHU=",
      "thumb": "UTb0sGqADnbLiHq9qhRMRkSRiLND0Tk7ctN8tpraiieAtUNCUH5eTv3YkL2lNVHUusmeOPUO9Ldw3Z3yzVaPh5Vy4706IhQgSYlgwrgVRHU=",
      "lt_id_alb": [
        "63410260"
      ],
      "list_id_nortag": [
        "-1182628656",
        "-1556851449"
      ],
      "lt_id_sptag": [
        "-1230434216",
        "-729883027",
        "-353024394",
        "1367612750",
        "-67611207",
        "-1165766878",
        "-1046579185",
        "1078827483",
        "2137211747"
      ]
    },
    {
      "hc_lt_id_alb": "-824026795",
      "hc_lt_id_nortag": "812550897",
      "hc_lt_id_sptag": "563717366",
      "id_img": "Original_846466_crop2608_-1508215078",
      "link_img": "UTb0sGqADnbLiHq9qhRMRkSRiLND0Tk7ctN8tpraiieuXGzkCvqEYr86vExNvsqhfZZMkiUA2lkIoyO7foguZpVy4706IhQgSYlgwrgVRHU=",
      "thumb": "UTb0sGqADnbLiHq9qhRMRkSRiLND0Tk7ctN8tpraiieuXGzkCvqEYr86vExNvsqhoQTKsGYpgFKxINmrPJ6ZiZVy4706IhQgSYlgwrgVRHU=",
      "lt_id_alb": [
        "63410260"
      ],
      "list_id_nortag": [
        "1023613280",
        "-1182628656"
      ],
      "lt_id_sptag": [
        "-1915687819",
        "-1377489872",
        "177416588",
        "-1230434216",
        "-1546073662",
        "117222074",
        "-353024394",
        "1367612750",
        "1913692055",
        "63311442",
        "-67611207",
        "-260062140",
        "-1823594757",
        "1078827483",
        "-1456680780",
        "491824726",
        "26918368",
        "467732324",
        "-1358769180"
      ]
    },
    {
      "hc_lt_id_alb": "-824026795",
      "hc_lt_id_nortag": "322817577",
      "hc_lt_id_sptag": "-1335536747",
      "id_img": "DagashiKashi_683463_crop2608_-696234640",
      "link_img": "UTb0sGqADnbLiHq9qhRMRkSRiLND0Tk7ctN8tpraiidi241R4fx01uh4KAGRybCVXdmUROMR1AtDTPjOvhkVXpVy4706IhQgSYlgwrgVRHU=",
      "thumb": "UTb0sGqADnbLiHq9qhRMRkSRiLND0Tk7ctN8tpraiidi241R4fx01uh4KAGRybCV1Df9ssGdoqkqirwBj9ovt5Vy4706IhQgSYlgwrgVRHU=",
      "lt_id_alb": [
        "63410260"
      ],
      "list_id_nortag": [
        "1095644500",
        "-1182628656"
      ],
      "lt_id_sptag": [
        "-1230434216",
        "1367612750",
        "376240968",
        "1913692055",
        "-260062140",
        "-1823594757",
        "1078827483",
        "-660511924",
        "1410951528"
      ]
    },
    {
      "hc_lt_id_alb": "-824026795",
      "hc_lt_id_nortag": "1896949049",
      "hc_lt_id_sptag": "1016635310",
      "id_img": "SoranoMukoudeSakimasuyouni_792722_crop2608_272617950",
      "link_img": "UTb0sGqADnbLiHq9qhRMRkSRiLND0Tk7ctN8tpraiidM4CxkbFqQAL7r4x2cxd3nqi64Yw+T5YsNHOH6oMkSXZVy4706IhQgSYlgwrgVRHU=",
      "thumb": "UTb0sGqADnbLiHq9qhRMRkSRiLND0Tk7ctN8tpraiidM4CxkbFqQAL7r4x2cxd3n5AXhOqgn7g4eWMPONddlYZVy4706IhQgSYlgwrgVRHU=",
      "lt_id_alb": [
        "63410260"
      ],
      "list_id_nortag": [
        "-1182628656",
        "-1441071755"
      ],
      "lt_id_sptag": [
        "-1393218324",
        "1496964037",
        "-1230434216",
        "-861082735",
        "-353024394",
        "1367612750",
        "376240968",
        "-67611207",
        "-290487968",
        "424585427",
        "-1165766878",
        "306423203",
        "1078827483",
        "2137211747"
      ]
    },
    {
      "hc_lt_id_alb": "-824026795",
      "hc_lt_id_nortag": "-1114397356",
      "hc_lt_id_sptag": "1541180375",
      "id_img": "Original_915091_crop2608_15750187",
      "link_img": "UTb0sGqADnbLiHq9qhRMRkSRiLND0Tk7ctN8tpraiidkNFL6ZbKSu4h2Azd9bab0r6uERlgaXTF8iBkRv7eF+ZVy4706IhQgSYlgwrgVRHU=",
      "thumb": "UTb0sGqADnbLiHq9qhRMRkSRiLND0Tk7ctN8tpraiidkNFL6ZbKSu4h2Azd9bab0EjBElVjHjJOIFHmzTHivPJVy4706IhQgSYlgwrgVRHU=",
      "lt_id_alb": [
        "63410260"
      ],
      "list_id_nortag": [
        "-669347768",
        "-1182628656"
      ],
      "lt_id_sptag": [
        "-333189356",
        "750914149",
        "-1230434216",
        "-729883027",
        "-353024394",
        "1367612750",
        "376240968",
        "-1686571485",
        "1078827483",
        "491824726"
      ]
    },
    {
      "hc_lt_id_alb": "-824026795",
      "hc_lt_id_nortag": "-913259641",
      "hc_lt_id_sptag": "1514125813",
      "id_img": "ChaikaTheCoffinPrincess_563701_crop2608_-146189745",
      "link_img": "UTb0sGqADnbLiHq9qhRMRkSRiLND0Tk7ctN8tpraiieVGcS1mc7EJFlK5kxxI+bDQ7A+uV2JSCJhFNcF/ILPwJVy4706IhQgSYlgwrgVRHU=",
      "thumb": "UTb0sGqADnbLiHq9qhRMRkSRiLND0Tk7ctN8tpraiieVGcS1mc7EJFlK5kxxI+bD82864iXMOiIl65UDlg7appVy4706IhQgSYlgwrgVRHU=",
      "lt_id_alb": [
        "63410260"
      ],
      "list_id_nortag": [
        "-163965883",
        "-1182628656"
      ],
      "lt_id_sptag": [
        "1271392973",
        "-464433724",
        "-729883027",
        "1367612750",
        "63311442",
        "-260062140",
        "-1823594757",
        "1649949488",
        "1078827483",
        "491824726",
        "1410951528"
      ]
    },
    {
      "hc_lt_id_alb": "-824026795",
      "hc_lt_id_nortag": "-1850314428",
      "hc_lt_id_sptag": "-1498842110",
      "id_img": "DateALive_578573_crop2608_1417767757",
      "link_img": "UTb0sGqADnbLiHq9qhRMRkSRiLND0Tk7ctN8tpraiictpuBVf6GDSZASBf6f+RKe/dzGdHqq+gyVLmI8/3qQ2pVy4706IhQgSYlgwrgVRHU=",
      "thumb": "UTb0sGqADnbLiHq9qhRMRkSRiLND0Tk7ctN8tpraiictpuBVf6GDSZASBf6f+RKeLLlXNBUZ8gy9p9QP71kwCZVy4706IhQgSYlgwrgVRHU=",
      "lt_id_alb": [
        "63410260"
      ],
      "list_id_nortag": [
        "-806183626",
        "-1182628656"
      ],
      "lt_id_sptag": [
        "1545739930",
        "-220048903",
        "937579079",
        "-1230434216",
        "1755521698",
        "-353024394",
        "1367612750",
        "-1686571485",
        "-1961656491",
        "1078827483",
        "-516908271",
        "904137049"
      ]
    },
    {
      "hc_lt_id_alb": "-824026795",
      "hc_lt_id_nortag": "501566065",
      "hc_lt_id_sptag": "1240035916",
      "id_img": "AvatarTheLastAirbender_753568_crop2608_-1259880751",
      "link_img": "UTb0sGqADnbLiHq9qhRMRkSRiLND0Tk7ctN8tpraiid3fI8OXVsVZGQEvnbPd+XJrWbx0ok65oj+RGG+X/P6jJVy4706IhQgSYlgwrgVRHU=",
      "thumb": "UTb0sGqADnbLiHq9qhRMRkSRiLND0Tk7ctN8tpraiid3fI8OXVsVZGQEvnbPd+XJbFev3o8WxAH4zHgOS5iGxpVy4706IhQgSYlgwrgVRHU=",
      "lt_id_alb": [
        "63410260"
      ],
      "list_id_nortag": [
        "353562101",
        "-1182628656"
      ],
      "lt_id_sptag": [
        "117222074",
        "1367612750",
        "-1686571485",
        "1097693819",
        "1410951528",
        "2058364749"
      ]
    },
    {
      "hc_lt_id_alb": "-824026795",
      "hc_lt_id_nortag": "-1114397356",
      "hc_lt_id_sptag": "-380650440",
      "id_img": "Original_925106_crop2608_-227747237",
      "link_img": "UTb0sGqADnbLiHq9qhRMRkSRiLND0Tk7ctN8tpraiidZMtVjg/wzhZf40ask3cbfPTFe1CjtJmbK0z8y7Xg5u5Vy4706IhQgSYlgwrgVRHU=",
      "thumb": "UTb0sGqADnbLiHq9qhRMRkSRiLND0Tk7ctN8tpraiidZMtVjg/wzhZf40ask3cbfGpGfVmt3m988IZAGob5lKZVy4706IhQgSYlgwrgVRHU=",
      "lt_id_alb": [
        "63410260"
      ],
      "list_id_nortag": [
        "-669347768",
        "-1182628656"
      ],
      "lt_id_sptag": [
        "-1439560410",
        "1367612750",
        "376240968",
        "-1686571485",
        "2026891902",
        "1078827483",
        "491824726",
        "1410951528"
      ]
    },
    {
      "hc_lt_id_alb": "-824026795",
      "hc_lt_id_nortag": "-1537437492",
      "hc_lt_id_sptag": "-1692310356",
      "id_img": "AIChannel_909203_crop2608_460727159",
      "link_img": "UTb0sGqADnbLiHq9qhRMRkSRiLND0Tk7ctN8tpraiif0ryPnhCSAA6MUA0I+hLkuYDeGY1FCXU1EYw8JwoCVV5Vy4706IhQgSYlgwrgVRHU=",
      "thumb": "UTb0sGqADnbLiHq9qhRMRkSRiLND0Tk7ctN8tpraiif0ryPnhCSAA6MUA0I+hLkuifFH8NLuAWowDanl0uivN5Vy4706IhQgSYlgwrgVRHU=",
      "lt_id_alb": [
        "63410260"
      ],
      "list_id_nortag": [
        "-1318058620",
        "-1182628656"
      ],
      "lt_id_sptag": [
        "-1230434216",
        "1298917365",
        "-353024394",
        "538504409",
        "1367612750",
        "376240968",
        "1913692055",
        "-67611207",
        "1813151526",
        "1078827483",
        "491824726",
        "26918368",
        "-1358769180"
      ]
    },
    {
      "hc_lt_id_alb": "-824026795",
      "hc_lt_id_nortag": "1325612124",
      "hc_lt_id_sptag": "-304623303",
      "id_img": "GranblueFantasy_692633_crop2608_-1695549468",
      "link_img": "UTb0sGqADnbLiHq9qhRMRkSRiLND0Tk7ctN8tpraiicy4BK96ceEOAD7TWxfhCPPpmFkD9RO6tYHsYczmEPb9JVy4706IhQgSYlgwrgVRHU=",
      "thumb": "UTb0sGqADnbLiHq9qhRMRkSRiLND0Tk7ctN8tpraiicy4BK96ceEOAD7TWxfhCPPEdh2xd8+K57aDF1drEiyBpVy4706IhQgSYlgwrgVRHU=",
      "lt_id_alb": [
        "63410260"
      ],
      "list_id_nortag": [
        "1658477201",
        "-1182628656"
      ],
      "lt_id_sptag": [
        "-104383318",
        "-1230434216",
        "-729883027",
        "-353024394",
        "1367612750",
        "-260062140",
        "-1165766878",
        "1078827483",
        "2137211747",
        "26918368",
        "467732324"
      ]
    },
    {
      "hc_lt_id_alb": "-824026795",
      "hc_lt_id_nortag": "-1114397356",
      "hc_lt_id_sptag": "486875886",
      "id_img": "Original_916756_crop2608_891872282",
      "link_img": "UTb0sGqADnbLiHq9qhRMRkSRiLND0Tk7ctN8tpraiicBZmE2fjuZ/PZ5lmqOgXGyAWKm4lUWYzQo/Jj1L8HRMJVy4706IhQgSYlgwrgVRHU=",
      "thumb": "UTb0sGqADnbLiHq9qhRMRkSRiLND0Tk7ctN8tpraiicBZmE2fjuZ/PZ5lmqOgXGymmdj6itm1SlHYhlxF3e7SJVy4706IhQgSYlgwrgVRHU=",
      "lt_id_alb": [
        "63410260"
      ],
      "list_id_nortag": [
        "-669347768",
        "-1182628656"
      ],
      "lt_id_sptag": [
        "1271392973",
        "-333189356",
        "-1216236529",
        "1367612750",
        "376240968",
        "1913692055",
        "1622667236",
        "680065126",
        "-1823594757",
        "1078827483",
        "1410951528"
      ]
    },
    {
      "hc_lt_id_alb": "-824026795",
      "hc_lt_id_nortag": "-1532318063",
      "hc_lt_id_sptag": "1287631726",
      "id_img": "SaekanoHowtoRaiseaBoringGirlfriend_679013_crop2608_-627059614",
      "link_img": "UTb0sGqADnbLiHq9qhRMRkSRiLND0Tk7ctN8tpraiid+8xqKdfTs3LRPMpVZvgILCmyTLpJCEbdxroptflR/jZVy4706IhQgSYlgwrgVRHU=",
      "thumb": "UTb0sGqADnbLiHq9qhRMRkSRiLND0Tk7ctN8tpraiid+8xqKdfTs3LRPMpVZvgILetmJhNSP97uXxmEJl2hCV5Vy4706IhQgSYlgwrgVRHU=",
      "lt_id_alb": [
        "63410260"
      ],
      "list_id_nortag": [
        "1589031968",
        "-1182628656"
      ],
      "lt_id_sptag": [
        "-1915687819",
        "29436897",
        "-353024394",
        "1367612750",
        "-1686571485",
        "-67611207",
        "1541647243",
        "1813151526",
        "891036203",
        "1078827483",
        "176756002"
      ]
    },
    {
      "hc_lt_id_alb": "-824026795",
      "hc_lt_id_nortag": "-2092928010",
      "hc_lt_id_sptag": "911336458",
      "id_img": "Original_907716_crop2608_-1513558788",
      "link_img": "UTb0sGqADnbLiHq9qhRMRkSRiLND0Tk7ctN8tpraiie2MWXSAqv3ORczuF6efHYlMk4Tji7ZwyVRS5AmocojYpVy4706IhQgSYlgwrgVRHU=",
      "thumb": "UTb0sGqADnbLiHq9qhRMRkSRiLND0Tk7ctN8tpraiie2MWXSAqv3ORczuF6efHYl31+XADy0E8BV7HiYERtHH5Vy4706IhQgSYlgwrgVRHU=",
      "lt_id_alb": [
        "63410260"
      ],
      "list_id_nortag": [
        "-1182628656",
        "-1556851449"
      ],
      "lt_id_sptag": [
        "-1915687819",
        "1545739930",
        "-587335586",
        "-353024394",
        "1367612750",
        "-67611207",
        "1813151526",
        "1447453426",
        "1078827483",
        "-1456680780",
        "491824726",
        "-1602093195"
      ]
    },
    {
      "hc_lt_id_alb": "-824026795",
      "hc_lt_id_nortag": "-822968574",
      "hc_lt_id_sptag": "2086421637",
      "id_img": "MissKobayashisDragonMaid_881181_crop2608_-1942292240",
      "link_img": "UTb0sGqADnbLiHq9qhRMRkSRiLND0Tk7ctN8tpraiifE3aflETEndRAYeD/pUQVc4Ea6DwOOJE6DCO6NrO5bwJVy4706IhQgSYlgwrgVRHU=",
      "thumb": "UTb0sGqADnbLiHq9qhRMRkSRiLND0Tk7ctN8tpraiifE3aflETEndRAYeD/pUQVcAXrGSW5o8sv8BVCxi54MwJVy4706IhQgSYlgwrgVRHU=",
      "lt_id_alb": [
        "63410260"
      ],
      "list_id_nortag": [
        "807641379",
        "-1182628656"
      ],
      "lt_id_sptag": [
        "702196920",
        "-1130112717",
        "-1230434216",
        "697180300",
        "-442593670",
        "-353024394",
        "1367612750",
        "246776394",
        "63311442",
        "-67611207",
        "1627623413",
        "1078827483",
        "-1456680780",
        "2137211747"
      ]
    },
    {
      "hc_lt_id_alb": "-824026795",
      "hc_lt_id_nortag": "322817577",
      "hc_lt_id_sptag": "2035674033",
      "id_img": "DagashiKashi_680943_crop2608_1492664666",
      "link_img": "UTb0sGqADnbLiHq9qhRMRkSRiLND0Tk7ctN8tpraiicrOuJAUNNfLOJT6REgGxqRBKTFGpATqKe+QHEYI/aULJVy4706IhQgSYlgwrgVRHU=",
      "thumb": "UTb0sGqADnbLiHq9qhRMRkSRiLND0Tk7ctN8tpraiicrOuJAUNNfLOJT6REgGxqREqjM0nbyucnhOQgWxIonYpVy4706IhQgSYlgwrgVRHU=",
      "lt_id_alb": [
        "63410260"
      ],
      "list_id_nortag": [
        "1095644500",
        "-1182628656"
      ],
      "lt_id_sptag": [
        "1367612750",
        "376240968",
        "-260062140",
        "-1823594757",
        "1078827483",
        "-660511924",
        "1410951528"
      ]
    },
    {
      "hc_lt_id_alb": "-824026795",
      "hc_lt_id_nortag": "-1114397356",
      "hc_lt_id_sptag": "1148005537",
      "id_img": "Original_915507_crop2608_-1052419361",
      "link_img": "UTb0sGqADnbLiHq9qhRMRkSRiLND0Tk7ctN8tpraiifZc5ld+bMXmGQvettzveh9fT8lFdWwJpxSx/batHxcr5Vy4706IhQgSYlgwrgVRHU=",
      "thumb": "UTb0sGqADnbLiHq9qhRMRkSRiLND0Tk7ctN8tpraiifZc5ld+bMXmGQvettzveh9hjHAI3XDPZ2yr9jrdwz68pVy4706IhQgSYlgwrgVRHU=",
      "lt_id_alb": [
        "63410260"
      ],
      "list_id_nortag": [
        "-669347768",
        "-1182628656"
      ],
      "lt_id_sptag": [
        "-333189356",
        "-729883027",
        "117222074",
        "-353024394",
        "1367612750",
        "1913692055",
        "1813151526",
        "-260062140",
        "-1455727370",
        "1078827483",
        "-1456680780",
        "-2046828957",
        "1039377061"
      ]
    }
  ],
  "lt_nortag": [
    {
      "id_nortag": "-1318058620",
      "name_cl_nortag": "AI Channel",
      "total_img": 22,
      "name_parent": "Anime"
    },
    {
      "id_nortag": "671033425",
      "name_cl_nortag": "Aikatsu",
      "total_img": 67,
      "name_parent": "Anime"
    },
    {
      "id_nortag": "-1485458249",
      "name_cl_nortag": "Angel Beats",
      "total_img": 387,
      "name_parent": "Anime"
    },
    {
      "id_nortag": "353562101",
      "name_cl_nortag": "Avatar The Last Airbender",
      "total_img": 19,
      "name_parent": "Anime"
    },
    {
      "id_nortag": "-1494515094",
      "name_cl_nortag": "Avatar The Legend Of Korra",
      "total_img": 20,
      "name_parent": "Anime"
    },
    {
      "id_nortag": "-684396608",
      "name_cl_nortag": "Boku Wa Tomodachi Ga Sukunai",
      "total_img": 54,
      "name_parent": "Anime"
    },
    {
      "id_nortag": "-467032699",
      "name_cl_nortag": "Boy",
      "total_img": 8592,
      "name_parent": "Anime"
    },
    {
      "id_nortag": "-163965883",
      "name_cl_nortag": "Chaika The Coffin Princess",
      "total_img": 16,
      "name_parent": "Anime"
    },
    {
      "id_nortag": "1095644500",
      "name_cl_nortag": "Dagashi Kashi",
      "total_img": 16,
      "name_parent": "Anime"
    },
    {
      "id_nortag": "-806183626",
      "name_cl_nortag": "Date A Live",
      "total_img": 157,
      "name_parent": "Anime"
    },
    {
      "id_nortag": "-1250415468",
      "name_cl_nortag": "Fairy Tail",
      "total_img": 184,
      "name_parent": "Anime"
    },
    {
      "id_nortag": "-1182628656",
      "name_cl_nortag": "Girls",
      "total_img": 68557,
      "name_parent": "Anime"
    },
    {
      "id_nortag": "1658477201",
      "name_cl_nortag": "Granblue Fantasy",
      "total_img": 44,
      "name_parent": "Anime"
    },
    {
      "id_nortag": "579558099",
      "name_cl_nortag": "Kantai Collection",
      "total_img": 1036,
      "name_parent": "Anime"
    },
    {
      "id_nortag": "807641379",
      "name_cl_nortag": "Miss Kobayashis Dragon Maid",
      "total_img": 99,
      "name_parent": "Anime"
    },
    {
      "id_nortag": "402664479",
      "name_cl_nortag": "Noragami",
      "total_img": 54,
      "name_parent": "Anime"
    },
    {
      "id_nortag": "-1166409139",
      "name_cl_nortag": "One Piece",
      "total_img": 283,
      "name_parent": "Anime"
    },
    {
      "id_nortag": "-1556851449",
      "name_cl_nortag": "Original 10",
      "total_img": 637,
      "name_parent": "Anime"
    },
    {
      "id_nortag": "-669347768",
      "name_cl_nortag": "Original 11",
      "total_img": 777,
      "name_parent": "Anime"
    },
    {
      "id_nortag": "-1638897763",
      "name_cl_nortag": "Original 3",
      "total_img": 1138,
      "name_parent": "Anime"
    },
    {
      "id_nortag": "1023613280",
      "name_cl_nortag": "Original 6",
      "total_img": 437,
      "name_parent": "Anime"
    },
    {
      "id_nortag": "-1823434899",
      "name_cl_nortag": "Puella Magi Madoka Magica",
      "total_img": 308,
      "name_parent": "Anime"
    },
    {
      "id_nortag": "-274114340",
      "name_cl_nortag": "ReZERO Starting Life in Another World",
      "total_img": 350,
      "name_parent": "Anime"
    },
    {
      "id_nortag": "1589031968",
      "name_cl_nortag": "Saekano How to Raise a Boring Girlfriend",
      "total_img": 103,
      "name_parent": "Anime"
    },
    {
      "id_nortag": "-1441071755",
      "name_cl_nortag": "Sora no Mukou de Sakimasu you ni",
      "total_img": 5,
      "name_parent": "Anime"
    },
    {
      "id_nortag": "22161571",
      "name_cl_nortag": "Sound Horizon",
      "total_img": 2,
      "name_parent": "Anime"
    },
    {
      "id_nortag": "882178788",
      "name_cl_nortag": "Tokyo Ghoul",
      "total_img": 279,
      "name_parent": "Anime"
    },
    {
      "id_nortag": "-843208019",
      "name_cl_nortag": "Touhou",
      "total_img": 1995,
      "name_parent": "Anime"
    },
    {
      "id_nortag": "-324062098",
      "name_cl_nortag": "Vocaloid",
      "total_img": 1338,
      "name_parent": "Anime"
    }
  ],
  "lt_sptag": [
    {
      "id_sptag": "-1372583199",
      "name_cl_sptag": "Akagi Kancolle",
      "name_parent": "Anime",
      "total": 38
    },
    {
      "id_sptag": "1857376909",
      "name_cl_sptag": "Alice Margatroid",
      "name_parent": "Anime",
      "total": 75
    },
    {
      "id_sptag": "424462971",
      "name_cl_sptag": "Apron",
      "name_parent": "Anime",
      "total": 64
    },
    {
      "id_sptag": "1457245087",
      "name_cl_sptag": "Aqua Eyes",
      "name_parent": "Anime",
      "total": 65
    },
    {
      "id_sptag": "-464433724",
      "name_cl_sptag": "Belt",
      "name_parent": "Anime",
      "total": 49
    },
    {
      "id_sptag": "1447453426",
      "name_cl_sptag": "Bird",
      "name_parent": "Anime",
      "total": 95
    },
    {
      "id_sptag": "-1025861007",
      "name_cl_sptag": "Bleached Eyes",
      "name_parent": "Anime",
      "total": 9
    },
    {
      "id_sptag": "2137211747",
      "name_cl_sptag": "Blonde",
      "name_parent": "Anime",
      "total": 908
    },
    {
      "id_sptag": "-67611207",
      "name_cl_sptag": "Blush",
      "name_parent": "Anime",
      "total": 893
    },
    {
      "id_sptag": "176756002",
      "name_cl_sptag": "Book",
      "name_parent": "Anime",
      "total": 116
    },
    {
      "id_sptag": "218089402",
      "name_cl_sptag": "Boots",
      "name_parent": "Anime",
      "total": 51
    },
    {
      "id_sptag": "1913692055",
      "name_cl_sptag": "bow Clothing",
      "name_parent": "Anime",
      "total": 452
    },
    {
      "id_sptag": "1039377061",
      "name_cl_sptag": "Braid",
      "name_parent": "Anime",
      "total": 149
    },
    {
      "id_sptag": "1722132917",
      "name_cl_sptag": "Cage",
      "name_parent": "Anime",
      "total": 1
    },
    {
      "id_sptag": "-104383318",
      "name_cl_sptag": "Cagliostro Granblue Fantasy",
      "name_parent": "Anime",
      "total": 8
    },
    {
      "id_sptag": "-587335586",
      "name_cl_sptag": "Camera",
      "name_parent": "Anime",
      "total": 19
    },
    {
      "id_sptag": "-1046579185",
      "name_cl_sptag": "Cat",
      "name_parent": "Anime",
      "total": 128
    },
    {
      "id_sptag": "-1602093195",
      "name_cl_sptag": "Cherry Blossom",
      "name_parent": "Anime",
      "total": 92
    },
    {
      "id_sptag": "937579079",
      "name_cl_sptag": "Clock",
      "name_parent": "Anime",
      "total": 8
    },
    {
      "id_sptag": "-1208878804",
      "name_cl_sptag": "CloseUp",
      "name_parent": "Anime",
      "total": 2
    },
    {
      "id_sptag": "-69431816",
      "name_cl_sptag": "Creature",
      "name_parent": "Anime",
      "total": 9
    },
    {
      "id_sptag": "-1377489872",
      "name_cl_sptag": "Crown",
      "name_parent": "Anime",
      "total": 35
    },
    {
      "id_sptag": "579965105",
      "name_cl_sptag": "Crying",
      "name_parent": "Anime",
      "total": 15
    },
    {
      "id_sptag": "-1176638482",
      "name_cl_sptag": "Dark Black",
      "name_parent": "Anime",
      "total": 4051
    },
    {
      "id_sptag": "-1085357263",
      "name_cl_sptag": "Earbuds",
      "name_parent": "Anime",
      "total": 5
    },
    {
      "id_sptag": "1414196206",
      "name_cl_sptag": "Endou Saya",
      "name_parent": "Anime",
      "total": 6
    },
    {
      "id_sptag": "1694271403",
      "name_cl_sptag": "Eriri Spencer Sawamura",
      "name_parent": "Anime",
      "total": 50
    },
    {
      "id_sptag": "-1730597006",
      "name_cl_sptag": "Eye Patch",
      "name_parent": "Anime",
      "total": 38
    },
    {
      "id_sptag": "-124333362",
      "name_cl_sptag": "Fairy",
      "name_parent": "Anime",
      "total": 12
    },
    {
      "id_sptag": "702196920",
      "name_cl_sptag": "Fangs",
      "name_parent": "Anime",
      "total": 22
    },
    {
      "id_sptag": "1168591711",
      "name_cl_sptag": "Fantasy",
      "name_parent": "Anime",
      "total": 83
    },
    {
      "id_sptag": "1090937228",
      "name_cl_sptag": "Fan",
      "name_parent": "Anime",
      "total": 28
    },
    {
      "id_sptag": "-1038892260",
      "name_cl_sptag": "Feather",
      "name_parent": "Anime",
      "total": 26
    },
    {
      "id_sptag": "-333189356",
      "name_cl_sptag": "Flower",
      "name_parent": "Anime",
      "total": 497
    },
    {
      "id_sptag": "1768110807",
      "name_cl_sptag": "Food",
      "name_parent": "Anime",
      "total": 51
    },
    {
      "id_sptag": "491824726",
      "name_cl_sptag": "Girls Cute Cool",
      "name_parent": "Anime",
      "total": 31431
    },
    {
      "id_sptag": "-1092439432",
      "name_cl_sptag": "Girls Dark",
      "name_parent": "Anime",
      "total": 3468
    },
    {
      "id_sptag": "1846426926",
      "name_cl_sptag": "Girls Ears Neko",
      "name_parent": "Anime",
      "total": 7031
    },
    {
      "id_sptag": "904137049",
      "name_cl_sptag": "Girls Eyes 2 Color",
      "name_parent": "Anime",
      "total": 656
    },
    {
      "id_sptag": "-899599709",
      "name_cl_sptag": "Girls Eyes Black",
      "name_parent": "Anime",
      "total": 5810
    },
    {
      "id_sptag": "376240968",
      "name_cl_sptag": "Girls Eyes Blue",
      "name_parent": "Anime",
      "total": 25656
    },
    {
      "id_sptag": "1545739930",
      "name_cl_sptag": "Girls Eyes Brown",
      "name_parent": "Anime",
      "total": 9376
    },
    {
      "id_sptag": "-111108595",
      "name_cl_sptag": "Girls Eyes Grey",
      "name_parent": "Anime",
      "total": 2483
    },
    {
      "id_sptag": "467732324",
      "name_cl_sptag": "Girls Eyes Pink",
      "name_parent": "Anime",
      "total": 1874
    },
    {
      "id_sptag": "-1915687819",
      "name_cl_sptag": "Girls Eyes Red",
      "name_parent": "Anime",
      "total": 12697
    },
    {
      "id_sptag": "1097693819",
      "name_cl_sptag": "Girls Eyes Silver",
      "name_parent": "Anime",
      "total": 1109
    },
    {
      "id_sptag": "-729883027",
      "name_cl_sptag": "Girls Eyes Violet",
      "name_parent": "Anime",
      "total": 6410
    },
    {
      "id_sptag": "2058364749",
      "name_cl_sptag": "Girls Eyes White",
      "name_parent": "Anime",
      "total": 133
    },
    {
      "id_sptag": "1755521698",
      "name_cl_sptag": "Girls Eyes Yellow",
      "name_parent": "Anime",
      "total": 6605
    },
    {
      "id_sptag": "-1439560410",
      "name_cl_sptag": "Girls Face Masks",
      "name_parent": "Anime",
      "total": 1618
    },
    {
      "id_sptag": "-561045702",
      "name_cl_sptag": "Girls Glasses",
      "name_parent": "Anime",
      "total": 2385
    },
    {
      "id_sptag": "538504409",
      "name_cl_sptag": "Girls Hair 2 Color",
      "name_parent": "Anime",
      "total": 1686
    },
    {
      "id_sptag": "-1686571485",
      "name_cl_sptag": "Girls Hair Black",
      "name_parent": "Anime",
      "total": 16737
    },
    {
      "id_sptag": "-1450260536",
      "name_cl_sptag": "Girls Hair Blue",
      "name_parent": "Anime",
      "total": 9528
    },
    {
      "id_sptag": "1813151526",
      "name_cl_sptag": "Girls Hair Brow",
      "name_parent": "Anime",
      "total": 13760
    },
    {
      "id_sptag": "-1937610099",
      "name_cl_sptag": "Girls Hair Grey",
      "name_parent": "Anime",
      "total": 9239
    },
    {
      "id_sptag": "-1353196196",
      "name_cl_sptag": "Girls Hair Orange",
      "name_parent": "Anime",
      "total": 4128
    },
    {
      "id_sptag": "-1358769180",
      "name_cl_sptag": "Girls Hair Pink",
      "name_parent": "Anime",
      "total": 5690
    },
    {
      "id_sptag": "1627623413",
      "name_cl_sptag": "Girls Hair Red",
      "name_parent": "Anime",
      "total": 3081
    },
    {
      "id_sptag": "-1823594757",
      "name_cl_sptag": "Girls Hair Silver",
      "name_parent": "Anime",
      "total": 16300
    },
    {
      "id_sptag": "643795693",
      "name_cl_sptag": "Girls Hair Violet",
      "name_parent": "Anime",
      "total": 2650
    },
    {
      "id_sptag": "1271392973",
      "name_cl_sptag": "Girls Hair White",
      "name_parent": "Anime",
      "total": 8666
    },
    {
      "id_sptag": "-1165766878",
      "name_cl_sptag": "Girls Hair Yellow",
      "name_parent": "Anime",
      "total": 12651
    },
    {
      "id_sptag": "117222074",
      "name_cl_sptag": "Girls Hats",
      "name_parent": "Anime",
      "total": 11965
    },
    {
      "id_sptag": "-442593670",
      "name_cl_sptag": "Girls Hoodie",
      "name_parent": "Anime",
      "total": 2667
    },
    {
      "id_sptag": "606716576",
      "name_cl_sptag": "Girls Horns",
      "name_parent": "Anime",
      "total": 2031
    },
    {
      "id_sptag": "750914149",
      "name_cl_sptag": "Girls Kimono Yukata Cheongsam",
      "name_parent": "Anime",
      "total": 7942
    },
    {
      "id_sptag": "-1546073662",
      "name_cl_sptag": "Girls Loli",
      "name_parent": "Anime",
      "total": 2098
    },
    {
      "id_sptag": "-353024394",
      "name_cl_sptag": "Girls Long Hair",
      "name_parent": "Anime",
      "total": 47407
    },
    {
      "id_sptag": "1010924017",
      "name_cl_sptag": "Girls Maid",
      "name_parent": "Anime",
      "total": 2625
    },
    {
      "id_sptag": "680065126",
      "name_cl_sptag": "Girls Sad",
      "name_parent": "Anime",
      "total": 10506
    },
    {
      "id_sptag": "-2017515920",
      "name_cl_sptag": "Girls Sharp Canine Tooth",
      "name_parent": "Anime",
      "total": 3202
    },
    {
      "id_sptag": "1410951528",
      "name_cl_sptag": "Girls Short Hair",
      "name_parent": "Anime",
      "total": 23769
    },
    {
      "id_sptag": "-1230434216",
      "name_cl_sptag": "Girls Smile",
      "name_parent": "Anime",
      "total": 24284
    },
    {
      "id_sptag": "1541647243",
      "name_cl_sptag": "Girls Student",
      "name_parent": "Anime",
      "total": 16308
    },
    {
      "id_sptag": "1526533345",
      "name_cl_sptag": "Girls Tears",
      "name_parent": "Anime",
      "total": 1511
    },
    {
      "id_sptag": "1078827483",
      "name_cl_sptag": "Girls Tie Bows",
      "name_parent": "Anime",
      "total": 61257
    },
    {
      "id_sptag": "-260062140",
      "name_cl_sptag": "Girls Uniform",
      "name_parent": "Anime",
      "total": 16929
    },
    {
      "id_sptag": "1508952095",
      "name_cl_sptag": "Girls Water Rain",
      "name_parent": "Anime",
      "total": 2954
    },
    {
      "id_sptag": "1622667236",
      "name_cl_sptag": "Girls Wedding",
      "name_parent": "Anime",
      "total": 2328
    },
    {
      "id_sptag": "-1882261033",
      "name_cl_sptag": "Girls Witch",
      "name_parent": "Anime",
      "total": 8338
    },
    {
      "id_sptag": "-2046828957",
      "name_cl_sptag": "Glasses",
      "name_parent": "Anime",
      "total": 150
    },
    {
      "id_sptag": "63311442",
      "name_cl_sptag": "Glove",
      "name_parent": "Anime",
      "total": 164
    },
    {
      "id_sptag": "1308072943",
      "name_cl_sptag": "Gothic",
      "name_parent": "Anime",
      "total": 14
    },
    {
      "id_sptag": "1320442351",
      "name_cl_sptag": "Grass",
      "name_parent": "Anime",
      "total": 19
    },
    {
      "id_sptag": "-220048903",
      "name_cl_sptag": "Gun",
      "name_parent": "Anime",
      "total": 55
    },
    {
      "id_sptag": "-1393218324",
      "name_cl_sptag": "Hairpin",
      "name_parent": "Anime",
      "total": 3
    },
    {
      "id_sptag": "1367612750",
      "name_cl_sptag": "Headband",
      "name_parent": "Anime",
      "total": 73
    },
    {
      "id_sptag": "1089393616",
      "name_cl_sptag": "Headdress",
      "name_parent": "Anime",
      "total": 52
    },
    {
      "id_sptag": "-516908271",
      "name_cl_sptag": "Heterochromia",
      "name_parent": "Anime",
      "total": 83
    },
    {
      "id_sptag": "-42452310",
      "name_cl_sptag": "High Heels",
      "name_parent": "Anime",
      "total": 13
    },
    {
      "id_sptag": "-1239845591",
      "name_cl_sptag": "Hinami Fueguchi",
      "name_parent": "Anime",
      "total": 9
    },
    {
      "id_sptag": "1945436082",
      "name_cl_sptag": "Hiryuu Kancolle",
      "name_parent": "Anime",
      "total": 18
    },
    {
      "id_sptag": "1037188654",
      "name_cl_sptag": "Homura Akemi",
      "name_parent": "Anime",
      "total": 230
    },
    {
      "id_sptag": "-1472410809",
      "name_cl_sptag": "Jacket",
      "name_parent": "Anime",
      "total": 31
    },
    {
      "id_sptag": "-1068725006",
      "name_cl_sptag": "Japanese Clothes",
      "name_parent": "Anime",
      "total": 98
    },
    {
      "id_sptag": "473789866",
      "name_cl_sptag": "Kaga Kancolle",
      "name_parent": "Anime",
      "total": 50
    },
    {
      "id_sptag": "1166680991",
      "name_cl_sptag": "Kagune Tokyo Ghoul",
      "name_parent": "Anime",
      "total": 27
    },
    {
      "id_sptag": "-247566452",
      "name_cl_sptag": "Kanade Tachibana",
      "name_parent": "Anime",
      "total": 216
    },
    {
      "id_sptag": "886532079",
      "name_cl_sptag": "Kanna Kamui",
      "name_parent": "Anime",
      "total": 75
    },
    {
      "id_sptag": "306423203",
      "name_cl_sptag": "Kanno Kou",
      "name_parent": "Anime",
      "total": 1
    },
    {
      "id_sptag": "148046112",
      "name_cl_sptag": "Katara Avatar",
      "name_parent": "Anime",
      "total": 6
    },
    {
      "id_sptag": "1171821264",
      "name_cl_sptag": "Ken Kaneki",
      "name_parent": "Anime",
      "total": 255
    },
    {
      "id_sptag": "1298917365",
      "name_cl_sptag": "Kizuna AI",
      "name_parent": "Anime",
      "total": 24
    },
    {
      "id_sptag": "1906474058",
      "name_cl_sptag": "Kobato Hasegawa",
      "name_parent": "Anime",
      "total": 12
    },
    {
      "id_sptag": "697180300",
      "name_cl_sptag": "Kobayashi Miss Kobayashis Dragon Maid",
      "name_parent": "Anime",
      "total": 13
    },
    {
      "id_sptag": "-1961656491",
      "name_cl_sptag": "Kurumi Tokisaki",
      "name_parent": "Anime",
      "total": 43
    },
    {
      "id_sptag": "-2024578405",
      "name_cl_sptag": "Kyoko Sakura",
      "name_parent": "Anime",
      "total": 176
    },
    {
      "id_sptag": "-1866523531",
      "name_cl_sptag": "Kyuubey Puella Magi Madoka Magica",
      "name_parent": "Anime",
      "total": 43
    },
    {
      "id_sptag": "-2147125825",
      "name_cl_sptag": "Lantern",
      "name_parent": "Anime",
      "total": 37
    },
    {
      "id_sptag": "1717628584",
      "name_cl_sptag": "Levy McGarden",
      "name_parent": "Anime",
      "total": 5
    },
    {
      "id_sptag": "935793454",
      "name_cl_sptag": "Luka Megurine",
      "name_parent": "Anime",
      "total": 124
    },
    {
      "id_sptag": "-678792093",
      "name_cl_sptag": "Lunch",
      "name_parent": "Anime",
      "total": 3
    },
    {
      "id_sptag": "641041541",
      "name_cl_sptag": "Madoka Kaname",
      "name_parent": "Anime",
      "total": 232
    },
    {
      "id_sptag": "1496964037",
      "name_cl_sptag": "Mahori Tsukasa",
      "name_parent": "Anime",
      "total": 1
    },
    {
      "id_sptag": "225940197",
      "name_cl_sptag": "Mask",
      "name_parent": "Anime",
      "total": 69
    },
    {
      "id_sptag": "1441067176",
      "name_cl_sptag": "Megumi Kato",
      "name_parent": "Anime",
      "total": 66
    },
    {
      "id_sptag": "2043573436",
      "name_cl_sptag": "Miko Outfit",
      "name_parent": "Anime",
      "total": 40
    },
    {
      "id_sptag": "-1669187985",
      "name_cl_sptag": "Nora Noragami",
      "name_parent": "Anime",
      "total": 4
    },
    {
      "id_sptag": "-1307705100",
      "name_cl_sptag": "Pantyhose",
      "name_parent": "Anime",
      "total": 89
    },
    {
      "id_sptag": "1677155011",
      "name_cl_sptag": "Petal",
      "name_parent": "Anime",
      "total": 70
    },
    {
      "id_sptag": "1613046064",
      "name_cl_sptag": "Pistol",
      "name_parent": "Anime",
      "total": 10
    },
    {
      "id_sptag": "1124215239",
      "name_cl_sptag": "Pointed Ears",
      "name_parent": "Anime",
      "total": 34
    },
    {
      "id_sptag": "424585427",
      "name_cl_sptag": "Ponytail",
      "name_parent": "Anime",
      "total": 108
    },
    {
      "id_sptag": "1552857583",
      "name_cl_sptag": "Rainbow",
      "name_parent": "Anime",
      "total": 23
    },
    {
      "id_sptag": "-172225030",
      "name_cl_sptag": "Rem ReZERO",
      "name_parent": "Anime",
      "total": 222
    },
    {
      "id_sptag": "866423119",
      "name_cl_sptag": "Ribbon",
      "name_parent": "Anime",
      "total": 156
    },
    {
      "id_sptag": "1428433125",
      "name_cl_sptag": "Roronoa Zoro",
      "name_parent": "Anime",
      "total": 75
    },
    {
      "id_sptag": "-1216236529",
      "name_cl_sptag": "Sad",
      "name_parent": "Anime",
      "total": 12057
    },
    {
      "id_sptag": "-343568313",
      "name_cl_sptag": "Sayaka Miki",
      "name_parent": "Anime",
      "total": 179
    },
    {
      "id_sptag": "29436897",
      "name_cl_sptag": "School Uniform",
      "name_parent": "Anime",
      "total": 467
    },
    {
      "id_sptag": "-660511924",
      "name_cl_sptag": "Shidare Hotaru",
      "name_parent": "Anime",
      "total": 19
    },
    {
      "id_sptag": "1649949488",
      "name_cl_sptag": "Shorts",
      "name_parent": "Anime",
      "total": 32
    },
    {
      "id_sptag": "-1152882625",
      "name_cl_sptag": "Shoukaku Kancolle",
      "name_parent": "Anime",
      "total": 29
    },
    {
      "id_sptag": "1623277449",
      "name_cl_sptag": "Shu Tsukiyama",
      "name_parent": "Anime",
      "total": 6
    },
    {
      "id_sptag": "-3839867",
      "name_cl_sptag": "Sitting",
      "name_parent": "Anime",
      "total": 61
    },
    {
      "id_sptag": "177416588",
      "name_cl_sptag": "Skirt",
      "name_parent": "Anime",
      "total": 368
    },
    {
      "id_sptag": "-414222762",
      "name_cl_sptag": "Skull",
      "name_parent": "Anime",
      "total": 14
    },
    {
      "id_sptag": "489705754",
      "name_cl_sptag": "Sky",
      "name_parent": "Anime",
      "total": 168
    },
    {
      "id_sptag": "2026891902",
      "name_cl_sptag": "Smartphone",
      "name_parent": "Anime",
      "total": 10
    },
    {
      "id_sptag": "-1980983817",
      "name_cl_sptag": "Snowfall",
      "name_parent": "Anime",
      "total": 16
    },
    {
      "id_sptag": "703590460",
      "name_cl_sptag": "Snow",
      "name_parent": "Anime",
      "total": 72
    },
    {
      "id_sptag": "1443880616",
      "name_cl_sptag": "Socks",
      "name_parent": "Anime",
      "total": 28
    },
    {
      "id_sptag": "-667683750",
      "name_cl_sptag": "Souryuu Kancolle",
      "name_parent": "Anime",
      "total": 16
    },
    {
      "id_sptag": "1004491673",
      "name_cl_sptag": "Staff",
      "name_parent": "Anime",
      "total": 25
    },
    {
      "id_sptag": "-1331370225",
      "name_cl_sptag": "Sunset",
      "name_parent": "Anime",
      "total": 51
    },
    {
      "id_sptag": "-1903341030",
      "name_cl_sptag": "Sweater",
      "name_parent": "Anime",
      "total": 11
    },
    {
      "id_sptag": "-1455727370",
      "name_cl_sptag": "Sword",
      "name_parent": "Anime",
      "total": 198
    },
    {
      "id_sptag": "1791116166",
      "name_cl_sptag": "Tattoo",
      "name_parent": "Anime",
      "total": 18
    },
    {
      "id_sptag": "1267158087",
      "name_cl_sptag": "Tea Cup",
      "name_parent": "Anime",
      "total": 18
    },
    {
      "id_sptag": "1414468990",
      "name_cl_sptag": "Teapot",
      "name_parent": "Anime",
      "total": 11
    },
    {
      "id_sptag": "246776394",
      "name_cl_sptag": "Tears",
      "name_parent": "Anime",
      "total": 46
    },
    {
      "id_sptag": "-375059391",
      "name_cl_sptag": "Teeth",
      "name_parent": "Anime",
      "total": 15
    },
    {
      "id_sptag": "26918368",
      "name_cl_sptag": "Thigh Highs",
      "name_parent": "Anime",
      "total": 211
    },
    {
      "id_sptag": "-1130112717",
      "name_cl_sptag": "Tohru Miss Kobayashis Dragon Maid",
      "name_parent": "Anime",
      "total": 59
    },
    {
      "id_sptag": "-1491861316",
      "name_cl_sptag": "Touka Kirishima",
      "name_parent": "Anime",
      "total": 89
    },
    {
      "id_sptag": "-1456680780",
      "name_cl_sptag": "Twintails",
      "name_parent": "Anime",
      "total": 386
    },
    {
      "id_sptag": "-1277319363",
      "name_cl_sptag": "Ultimate Madoka",
      "name_parent": "Anime",
      "total": 25
    },
    {
      "id_sptag": "-290487968",
      "name_cl_sptag": "Urara Haruki",
      "name_parent": "Anime",
      "total": 3
    },
    {
      "id_sptag": "891036203",
      "name_cl_sptag": "Utaha Kasumigaoka",
      "name_parent": "Anime",
      "total": 45
    },
    {
      "id_sptag": "-2114154352",
      "name_cl_sptag": "Water",
      "name_parent": "Anime",
      "total": 98
    },
    {
      "id_sptag": "-1353313151",
      "name_cl_sptag": "Wings",
      "name_parent": "Anime",
      "total": 124
    },
    {
      "id_sptag": "-861082735",
      "name_cl_sptag": "Yae Renjou",
      "name_parent": "Anime",
      "total": 2
    },
    {
      "id_sptag": "-1995563546",
      "name_cl_sptag": "Yuri Nakamura",
      "name_parent": "Anime",
      "total": 82
    },
    {
      "id_sptag": "-1042073588",
      "name_cl_sptag": "Zuikaku Kancolle",
      "name_parent": "Anime",
      "total": 30
    },
    {
      "id_sptag": "-1612212205",
      "name_cl_sptag": "Zuko Avatar",
      "name_parent": "Anime",
      "total": 4
    }
  ]
}